{
  "安顺-西秀区": [
    {
      "姓名": "sf_程松松-架",
      "装维账号": "13238510565",
      "网格": "西秀区城区代维驻点城区网格",
      "日期": "3月",
      "呼入总量": 306,
      "一次接听量": 133,
      "一次接听率": 43.46,
      "回拨次数": 68,
      "真实接听率": 65.69,
      "真实未接通次数": 105
    },
    {
      "姓名": "吴春",
      "装维账号": "13678532453",
      "网格": "西秀区城区代维驻点集客家客维护组4",
      "日期": "3月",
      "呼入总量": 11,
      "一次接听量": 7,
      "一次接听率": 63.64,
      "回拨次数": 0,
      "真实接听率": 63.64,
      "真实未接通次数": 4
    },
    {
      "姓名": "/",
      "装维账号": "15718530758",
      "网格": "西秀区",
      "日期": "3月",
      "呼入总量": 9,
      "一次接听量": 1,
      "一次接听率": 11.11,
      "回拨次数": 0,
      "真实接听率": 11.11,
      "真实未接通次数": 8
    },
    {
      "姓名": "郭德斌",
      "装维账号": "15718530779",
      "网格": "西秀区城区代维驻点城区网格",
      "日期": "3月",
      "呼入总量": 114,
      "一次接听量": 32,
      "一次接听率": 28.07,
      "回拨次数": 47,
      "真实接听率": 69.3,
      "真实未接通次数": 35
    },
    {
      "姓名": "方八一",
      "装维账号": "18285381288",
      "网格": "西秀区城区代维驻点集客家客维护组4",
      "日期": "3月",
      "呼入总量": 250,
      "一次接听量": 113,
      "一次接听率": 45.2,
      "回拨次数": 30,
      "真实接听率": 57.2,
      "真实未接通次数": 107
    },
    {
      "姓名": "sf_张要春-黄应忠",
      "装维账号": "18286396310",
      "网格": "西秀区城区代维驻点集客家客维护组4",
      "日期": "3月",
      "呼入总量": 436,
      "一次接听量": 97,
      "一次接听率": 22.25,
      "回拨次数": 134,
      "真实接听率": 52.98,
      "真实未接通次数": 205
    },
    {
      "姓名": "/",
      "装维账号": "18722745013",
      "网格": "西秀区",
      "日期": "3月",
      "呼入总量": 98,
      "一次接听量": 44,
      "一次接听率": 44.9,
      "回拨次数": 5,
      "真实接听率": 50.0,
      "真实未接通次数": 49
    },
    {
      "姓名": "/",
      "装维账号": "19508554424",
      "网格": "西秀区",
      "日期": "3月",
      "呼入总量": 2,
      "一次接听量": 1,
      "一次接听率": 50.0,
      "回拨次数": 0,
      "真实接听率": 50.0,
      "真实未接通次数": 1
    }
  ],
  "安顺-普定县": [
    {
      "姓名": "陈康",
      "装维账号": "15185397288",
      "网格": "普定县城区代维驻点集客家客维护组1",
      "日期": "3月",
      "呼入总量": 112,
      "一次接听量": 66,
      "一次接听率": 58.93,
      "回拨次数": 10,
      "真实接听率": 67.86,
      "真实未接通次数": 36
    },
    {
      "姓名": "/",
      "装维账号": "18722741786",
      "网格": "普定县",
      "日期": "3月",
      "呼入总量": 21,
      "一次接听量": 1,
      "一次接听率": 4.76,
      "回拨次数": 0,
      "真实接听率": 4.76,
      "真实未接通次数": 20
    }
  ],
  "安顺-关岭县": [
    {
      "姓名": "/",
      "装维账号": "15185421761",
      "网格": "关岭县",
      "日期": "3月",
      "呼入总量": 46,
      "一次接听量": 8,
      "一次接听率": 17.39,
      "回拨次数": 4,
      "真实接听率": 26.09,
      "真实未接通次数": 34
    },
    {
      "姓名": "王文都",
      "装维账号": "15185431127",
      "网格": "关岭县城区代维驻点集客家客维护组1",
      "日期": "3月",
      "呼入总量": 60,
      "一次接听量": 24,
      "一次接听率": 40.0,
      "回拨次数": 14,
      "真实接听率": 63.33,
      "真实未接通次数": 22
    },
    {
      "姓名": "赵友华",
      "装维账号": "18722740450",
      "网格": "关岭县城区代维驻点集客家客维护组3",
      "日期": "3月",
      "呼入总量": 5,
      "一次接听量": 2,
      "一次接听率": 40.0,
      "回拨次数": 0,
      "真实接听率": 40.0,
      "真实未接通次数": 3
    },
    {
      "姓名": "朱松桃",
      "装维账号": "18722740520",
      "网格": "关岭县城区代维驻点集客家客维护组3",
      "日期": "3月",
      "呼入总量": 60,
      "一次接听量": 26,
      "一次接听率": 43.33,
      "回拨次数": 13,
      "真实接听率": 65.0,
      "真实未接通次数": 21
    }
  ],
  "安顺-平坝县": [
    {
      "姓名": "sf_刘一定",
      "装维账号": "15902534119",
      "网格": "平坝县城区代维驻点集客家客维护组1",
      "日期": "3月",
      "呼入总量": 23,
      "一次接听量": 1,
      "一次接听率": 4.35,
      "回拨次数": 0,
      "真实接听率": 4.35,
      "真实未接通次数": 22
    },
    {
      "姓名": "赵建",
      "装维账号": "18722740783",
      "网格": "平坝县城区代维驻点集客家客维护组1",
      "日期": "3月",
      "呼入总量": 2,
      "一次接听量": 1,
      "一次接听率": 50.0,
      "回拨次数": 0,
      "真实接听率": 50.0,
      "真实未接通次数": 1
    }
  ],
  "安顺-紫云县": [
    {
      "姓名": "吴永林",
      "装维账号": "18224699402",
      "网格": "紫云县城区代维驻点集客家客维护组1",
      "日期": "3月",
      "呼入总量": 49,
      "一次接听量": 26,
      "一次接听率": 53.06,
      "回拨次数": 4,
      "真实接听率": 61.22,
      "真实未接通次数": 19
    },
    {
      "姓名": "/",
      "装维账号": "18722742248",
      "网格": "紫云县",
      "日期": "3月",
      "呼入总量": 41,
      "一次接听量": 9,
      "一次接听率": 21.95,
      "回拨次数": 10,
      "真实接听率": 46.34,
      "真实未接通次数": 22
    },
    {
      "姓名": "/",
      "装维账号": "18722743579",
      "网格": "紫云县",
      "日期": "3月",
      "呼入总量": 12,
      "一次接听量": 4,
      "一次接听率": 33.33,
      "回拨次数": 0,
      "真实接听率": 33.33,
      "真实未接通次数": 8
    }
  ],
  "安顺-镇宁县": [
    {
      "姓名": "/",
      "装维账号": "18722741317",
      "网格": "镇宁县",
      "日期": "3月",
      "呼入总量": 8,
      "一次接听量": 3,
      "一次接听率": 37.5,
      "回拨次数": 0,
      "真实接听率": 37.5,
      "真实未接通次数": 5
    }
  ],
  "黔南-罗甸县": [
    {
      "姓名": "/",
      "装维账号": "13518548020",
      "网格": "罗甸县",
      "日期": "3月",
      "呼入总量": 12,
      "一次接听量": 6,
      "一次接听率": 50.0,
      "回拨次数": 2,
      "真实接听率": 66.67,
      "真实未接通次数": 4
    }
  ],
  "黔南-平塘县": [
    {
      "姓名": "/",
      "装维账号": "13765428605",
      "网格": "平塘县",
      "日期": "3月",
      "呼入总量": 20,
      "一次接听量": 11,
      "一次接听率": 55.0,
      "回拨次数": 1,
      "真实接听率": 60.0,
      "真实未接通次数": 8
    }
  ],
  "黔南-独山县": [
    {
      "姓名": "/",
      "装维账号": "13765796024",
      "网格": "独山县",
      "日期": "3月",
      "呼入总量": 95,
      "一次接听量": 17,
      "一次接听率": 17.89,
      "回拨次数": 39,
      "真实接听率": 58.95,
      "真实未接通次数": 39
    },
    {
      "姓名": "/",
      "装维账号": "18885483552",
      "网格": "独山县",
      "日期": "3月",
      "呼入总量": 19,
      "一次接听量": 1,
      "一次接听率": 5.26,
      "回拨次数": 0,
      "真实接听率": 5.26,
      "真实未接通次数": 18
    },
    {
      "姓名": "/",
      "装维账号": "18885485526",
      "网格": "独山县",
      "日期": "3月",
      "呼入总量": 20,
      "一次接听量": 4,
      "一次接听率": 20.0,
      "回拨次数": 0,
      "真实接听率": 20.0,
      "真实未接通次数": 16
    },
    {
      "姓名": "/",
      "装维账号": "18885489509",
      "网格": "独山县",
      "日期": "3月",
      "呼入总量": 16,
      "一次接听量": 8,
      "一次接听率": 50.0,
      "回拨次数": 3,
      "真实接听率": 68.75,
      "真实未接通次数": 5
    },
    {
      "姓名": "/",
      "装维账号": "18886483315",
      "网格": "独山县",
      "日期": "3月",
      "呼入总量": 11,
      "一次接听量": 3,
      "一次接听率": 27.27,
      "回拨次数": 0,
      "真实接听率": 27.27,
      "真实未接通次数": 8
    }
  ],
  "黔南-荔波县": [
    {
      "姓名": "/",
      "装维账号": "14708540552",
      "网格": "荔波县",
      "日期": "3月",
      "呼入总量": 130,
      "一次接听量": 27,
      "一次接听率": 20.77,
      "回拨次数": 22,
      "真实接听率": 37.69,
      "真实未接通次数": 81
    }
  ],
  "黔南-都匀市": [
    {
      "姓名": "/",
      "装维账号": "14785639736",
      "网格": "都匀市",
      "日期": "3月",
      "呼入总量": 21,
      "一次接听量": 6,
      "一次接听率": 28.57,
      "回拨次数": 3,
      "真实接听率": 42.86,
      "真实未接通次数": 12
    },
    {
      "姓名": "张海铭",
      "装维账号": "14785639916",
      "网格": "都匀市城区区信中心维护组",
      "日期": "3月",
      "呼入总量": 126,
      "一次接听量": 28,
      "一次接听率": 22.22,
      "回拨次数": 54,
      "真实接听率": 65.08,
      "真实未接通次数": 44
    },
    {
      "姓名": "/",
      "装维账号": "15085143544",
      "网格": "都匀市",
      "日期": "3月",
      "呼入总量": 13,
      "一次接听量": 8,
      "一次接听率": 61.54,
      "回拨次数": 1,
      "真实接听率": 69.23,
      "真实未接通次数": 4
    },
    {
      "姓名": "/",
      "装维账号": "18375196389",
      "网格": "都匀市",
      "日期": "3月",
      "呼入总量": 2,
      "一次接听量": 1,
      "一次接听率": 50.0,
      "回拨次数": 0,
      "真实接听率": 50.0,
      "真实未接通次数": 1
    }
  ],
  "黔南-龙里县": [
    {
      "姓名": "sf_何忠海",
      "装维账号": "15085155734",
      "网格": "都匀市平浪区信中心维护组",
      "日期": "3月",
      "呼入总量": 15,
      "一次接听量": 2,
      "一次接听率": 13.33,
      "回拨次数": 5,
      "真实接听率": 46.67,
      "真实未接通次数": 8
    },
    {
      "姓名": "/",
      "装维账号": "18224865597",
      "网格": "龙里县",
      "日期": "3月",
      "呼入总量": 10,
      "一次接听量": 3,
      "一次接听率": 30.0,
      "回拨次数": 3,
      "真实接听率": 60.0,
      "真实未接通次数": 4
    },
    {
      "姓名": "/",
      "装维账号": "18375209030",
      "网格": "龙里县",
      "日期": "3月",
      "呼入总量": 26,
      "一次接听量": 11,
      "一次接听率": 42.31,
      "回拨次数": 7,
      "真实接听率": 69.23,
      "真实未接通次数": 8
    }
  ],
  "黔南-贵定县": [
    {
      "姓名": "/",
      "装维账号": "15117840042",
      "网格": "贵定县",
      "日期": "3月",
      "呼入总量": 9,
      "一次接听量": 0,
      "一次接听率": 0.0,
      "回拨次数": 2,
      "真实接听率": 22.22,
      "真实未接通次数": 7
    }
  ],
  "黔南-惠水县": [
    {
      "姓名": "/",
      "装维账号": "15185451465",
      "网格": "惠水县",
      "日期": "3月",
      "呼入总量": 10,
      "一次接听量": 3,
      "一次接听率": 30.0,
      "回拨次数": 2,
      "真实接听率": 50.0,
      "真实未接通次数": 5
    },
    {
      "姓名": "/",
      "装维账号": "17886171825",
      "网格": "惠水县",
      "日期": "3月",
      "呼入总量": 22,
      "一次接听量": 8,
      "一次接听率": 36.36,
      "回拨次数": 3,
      "真实接听率": 50.0,
      "真实未接通次数": 11
    },
    {
      "姓名": "/",
      "装维账号": "18375196151",
      "网格": "惠水县",
      "日期": "3月",
      "呼入总量": 3,
      "一次接听量": 2,
      "一次接听率": 66.67,
      "回拨次数": 0,
      "真实接听率": 66.67,
      "真实未接通次数": 1
    },
    {
      "姓名": "/",
      "装维账号": "18798253144",
      "网格": "惠水县",
      "日期": "3月",
      "呼入总量": 61,
      "一次接听量": 4,
      "一次接听率": 6.56,
      "回拨次数": 14,
      "真实接听率": 29.51,
      "真实未接通次数": 43
    }
  ],
  "黔南-长顺县": [
    {
      "姓名": "/",
      "装维账号": "15285322202",
      "网格": "长顺县",
      "日期": "3月",
      "呼入总量": 69,
      "一次接听量": 34,
      "一次接听率": 49.28,
      "回拨次数": 14,
      "真实接听率": 69.57,
      "真实未接通次数": 21
    },
    {
      "姓名": "班康乾",
      "装维账号": "18285471422",
      "网格": "长顺县县城区信中心维护组",
      "日期": "3月",
      "呼入总量": 106,
      "一次接听量": 31,
      "一次接听率": 29.25,
      "回拨次数": 36,
      "真实接听率": 63.21,
      "真实未接通次数": 39
    }
  ],
  "黔南-瓮安县": [
    {
      "姓名": "/",
      "装维账号": "15885452683",
      "网格": "瓮安县",
      "日期": "3月",
      "呼入总量": 114,
      "一次接听量": 11,
      "一次接听率": 9.65,
      "回拨次数": 12,
      "真实接听率": 20.18,
      "真实未接通次数": 91
    },
    {
      "姓名": "王勇",
      "装维账号": "18885497039",
      "网格": "瓮安县锦美区信中心维护组",
      "日期": "3月",
      "呼入总量": 129,
      "一次接听量": 39,
      "一次接听率": 30.23,
      "回拨次数": 33,
      "真实接听率": 55.81,
      "真实未接通次数": 57
    },
    {
      "姓名": "/",
      "装维账号": "18885497257",
      "网格": "瓮安县",
      "日期": "3月",
      "呼入总量": 15,
      "一次接听量": 1,
      "一次接听率": 6.67,
      "回拨次数": 0,
      "真实接听率": 6.67,
      "真实未接通次数": 14
    }
  ],
  "黔南-三都县": [
    {
      "姓名": "/",
      "装维账号": "15885595562",
      "网格": "三都县",
      "日期": "3月",
      "呼入总量": 37,
      "一次接听量": 9,
      "一次接听率": 24.32,
      "回拨次数": 0,
      "真实接听率": 24.32,
      "真实未接通次数": 28
    },
    {
      "姓名": "/",
      "装维账号": "18285474559",
      "网格": "三都县",
      "日期": "3月",
      "呼入总量": 21,
      "一次接听量": 9,
      "一次接听率": 42.86,
      "回拨次数": 0,
      "真实接听率": 42.86,
      "真实未接通次数": 12
    },
    {
      "姓名": "/",
      "装维账号": "18375197809",
      "网格": "三都县",
      "日期": "3月",
      "呼入总量": 15,
      "一次接听量": 0,
      "一次接听率": 0.0,
      "回拨次数": 6,
      "真实接听率": 40.0,
      "真实未接通次数": 9
    },
    {
      "姓名": "/",
      "装维账号": "19885871369",
      "网格": "三都县",
      "日期": "3月",
      "呼入总量": 17,
      "一次接听量": 4,
      "一次接听率": 23.53,
      "回拨次数": 0,
      "真实接听率": 23.53,
      "真实未接通次数": 13
    }
  ],
  "黔南-福泉市": [
    {
      "姓名": "/",
      "装维账号": "18485360051",
      "网格": "福泉市",
      "日期": "3月",
      "呼入总量": 12,
      "一次接听量": 6,
      "一次接听率": 50.0,
      "回拨次数": 0,
      "真实接听率": 50.0,
      "真实未接通次数": 6
    },
    {
      "姓名": "/",
      "装维账号": "18485360617",
      "网格": "福泉市",
      "日期": "3月",
      "呼入总量": 38,
      "一次接听量": 14,
      "一次接听率": 36.84,
      "回拨次数": 0,
      "真实接听率": 36.84,
      "真实未接通次数": 24
    },
    {
      "姓名": "/",
      "装维账号": "18485360902",
      "网格": "福泉市",
      "日期": "3月",
      "呼入总量": 25,
      "一次接听量": 6,
      "一次接听率": 24.0,
      "回拨次数": 10,
      "真实接听率": 64.0,
      "真实未接通次数": 9
    },
    {
      "姓名": "/",
      "装维账号": "18485361037",
      "网格": "福泉市",
      "日期": "3月",
      "呼入总量": 127,
      "一次接听量": 21,
      "一次接听率": 16.54,
      "回拨次数": 35,
      "真实接听率": 44.09,
      "真实未接通次数": 71
    }
  ],
  "贵阳-修文县": [
    {
      "姓名": "/",
      "装维账号": "13595074739",
      "网格": "修文县",
      "日期": "3月",
      "呼入总量": 3,
      "一次接听量": 1,
      "一次接听率": 33.33,
      "回拨次数": 0,
      "真实接听率": 33.33,
      "真实未接通次数": 2
    },
    {
      "姓名": "/",
      "装维账号": "13608592140",
      "网格": "修文县",
      "日期": "3月",
      "呼入总量": 61,
      "一次接听量": 7,
      "一次接听率": 11.48,
      "回拨次数": 2,
      "真实接听率": 14.75,
      "真实未接通次数": 52
    },
    {
      "姓名": "/",
      "装维账号": "18285114560",
      "网格": "修文县",
      "日期": "3月",
      "呼入总量": 99,
      "一次接听量": 54,
      "一次接听率": 54.55,
      "回拨次数": 6,
      "真实接听率": 60.61,
      "真实未接通次数": 39
    },
    {
      "姓名": "/",
      "装维账号": "18302508529",
      "网格": "修文县",
      "日期": "3月",
      "呼入总量": 7,
      "一次接听量": 4,
      "一次接听率": 57.14,
      "回拨次数": 0,
      "真实接听率": 57.14,
      "真实未接通次数": 3
    },
    {
      "姓名": "/",
      "装维账号": "18302508532",
      "网格": "修文县",
      "日期": "3月",
      "呼入总量": 3,
      "一次接听量": 0,
      "一次接听率": 0.0,
      "回拨次数": 1,
      "真实接听率": 33.33,
      "真实未接通次数": 2
    }
  ],
  "贵阳-开阳县": [
    {
      "姓名": "/",
      "装维账号": "13608589462",
      "网格": "开阳县",
      "日期": "3月",
      "呼入总量": 17,
      "一次接听量": 10,
      "一次接听率": 58.82,
      "回拨次数": 0,
      "真实接听率": 58.82,
      "真实未接通次数": 7
    },
    {
      "姓名": "/",
      "装维账号": "13608592427",
      "网格": "开阳县",
      "日期": "3月",
      "呼入总量": 9,
      "一次接听量": 6,
      "一次接听率": 66.67,
      "回拨次数": 0,
      "真实接听率": 66.67,
      "真实未接通次数": 3
    },
    {
      "姓名": "/",
      "装维账号": "13608595042",
      "网格": "开阳县",
      "日期": "3月",
      "呼入总量": 34,
      "一次接听量": 14,
      "一次接听率": 41.18,
      "回拨次数": 2,
      "真实接听率": 47.06,
      "真实未接通次数": 18
    },
    {
      "姓名": "/",
      "装维账号": "18212027453",
      "网格": "开阳县",
      "日期": "3月",
      "呼入总量": 37,
      "一次接听量": 9,
      "一次接听率": 24.32,
      "回拨次数": 15,
      "真实接听率": 64.86,
      "真实未接通次数": 13
    },
    {
      "姓名": "/",
      "装维账号": "18302508468",
      "网格": "开阳县",
      "日期": "3月",
      "呼入总量": 25,
      "一次接听量": 8,
      "一次接听率": 32.0,
      "回拨次数": 9,
      "真实接听率": 68.0,
      "真实未接通次数": 8
    },
    {
      "姓名": "/",
      "装维账号": "18302508563",
      "网格": "开阳县",
      "日期": "3月",
      "呼入总量": 128,
      "一次接听量": 54,
      "一次接听率": 42.19,
      "回拨次数": 20,
      "真实接听率": 57.81,
      "真实未接通次数": 54
    },
    {
      "姓名": "/",
      "装维账号": "18302508564",
      "网格": "开阳县",
      "日期": "3月",
      "呼入总量": 16,
      "一次接听量": 8,
      "一次接听率": 50.0,
      "回拨次数": 0,
      "真实接听率": 50.0,
      "真实未接通次数": 8
    }
  ],
  "贵阳-息烽县": [
    {
      "姓名": "朱晶晶",
      "装维账号": "13765161314",
      "网格": "永靖社区网格",
      "日期": "3月",
      "呼入总量": 258,
      "一次接听量": 74,
      "一次接听率": 28.68,
      "回拨次数": 98,
      "真实接听率": 66.67,
      "真实未接通次数": 86
    }
  ],
  "贵阳-清镇市": [
    {
      "姓名": "赵明凯",
      "装维账号": "14785094404",
      "网格": "清镇城区网格",
      "日期": "3月",
      "呼入总量": 46,
      "一次接听量": 24,
      "一次接听率": 52.17,
      "回拨次数": 3,
      "真实接听率": 58.7,
      "真实未接通次数": 19
    },
    {
      "姓名": "/",
      "装维账号": "15885528422",
      "网格": "清镇市",
      "日期": "3月",
      "呼入总量": 7,
      "一次接听量": 3,
      "一次接听率": 42.86,
      "回拨次数": 0,
      "真实接听率": 42.86,
      "真实未接通次数": 4
    },
    {
      "姓名": "/",
      "装维账号": "18275317379",
      "网格": "清镇市",
      "日期": "3月",
      "呼入总量": 169,
      "一次接听量": 62,
      "一次接听率": 36.69,
      "回拨次数": 39,
      "真实接听率": 59.76,
      "真实未接通次数": 68
    },
    {
      "姓名": "/",
      "装维账号": "18285041672",
      "网格": "清镇市",
      "日期": "3月",
      "呼入总量": 31,
      "一次接听量": 11,
      "一次接听率": 35.48,
      "回拨次数": 4,
      "真实接听率": 48.39,
      "真实未接通次数": 16
    }
  ],
  "贵阳-南明区": [
    {
      "姓名": "/",
      "装维账号": "15285554142",
      "网格": "南明区",
      "日期": "3月",
      "呼入总量": 35,
      "一次接听量": 14,
      "一次接听率": 40.0,
      "回拨次数": 5,
      "真实接听率": 54.29,
      "真实未接通次数": 16
    },
    {
      "姓名": "/",
      "装维账号": "15285975949",
      "网格": "南明区",
      "日期": "3月",
      "呼入总量": 99,
      "一次接听量": 23,
      "一次接听率": 23.23,
      "回拨次数": 5,
      "真实接听率": 28.28,
      "真实未接通次数": 71
    },
    {
      "姓名": "韦开鹏",
      "装维账号": "18286389688",
      "网格": "南明外环社区网格",
      "日期": "3月",
      "呼入总量": 152,
      "一次接听量": 23,
      "一次接听率": 15.13,
      "回拨次数": 46,
      "真实接听率": 45.39,
      "真实未接通次数": 83
    },
    {
      "姓名": "/",
      "装维账号": "18302508623",
      "网格": "南明区",
      "日期": "3月",
      "呼入总量": 66,
      "一次接听量": 9,
      "一次接听率": 13.64,
      "回拨次数": 35,
      "真实接听率": 66.67,
      "真实未接通次数": 22
    }
  ],
  "贵阳-云岩区": [
    {
      "姓名": "/",
      "装维账号": "18212012254",
      "网格": "云岩区",
      "日期": "3月",
      "呼入总量": 15,
      "一次接听量": 5,
      "一次接听率": 33.33,
      "回拨次数": 0,
      "真实接听率": 33.33,
      "真实未接通次数": 10
    },
    {
      "姓名": "/",
      "装维账号": "18285131423",
      "网格": "云岩区",
      "日期": "3月",
      "呼入总量": 8,
      "一次接听量": 2,
      "一次接听率": 25.0,
      "回拨次数": 0,
      "真实接听率": 25.0,
      "真实未接通次数": 6
    },
    {
      "姓名": "/",
      "装维账号": "18285165969",
      "网格": "云岩区",
      "日期": "3月",
      "呼入总量": 40,
      "一次接听量": 2,
      "一次接听率": 5.0,
      "回拨次数": 3,
      "真实接听率": 12.5,
      "真实未接通次数": 35
    },
    {
      "姓名": "/",
      "装维账号": "18300896964",
      "网格": "云岩区",
      "日期": "3月",
      "呼入总量": 6,
      "一次接听量": 2,
      "一次接听率": 33.33,
      "回拨次数": 0,
      "真实接听率": 33.33,
      "真实未接通次数": 4
    },
    {
      "姓名": "/",
      "装维账号": "18300897024",
      "网格": "云岩区",
      "日期": "3月",
      "呼入总量": 41,
      "一次接听量": 13,
      "一次接听率": 31.71,
      "回拨次数": 6,
      "真实接听率": 46.34,
      "真实未接通次数": 22
    },
    {
      "姓名": "/",
      "装维账号": "18300897434",
      "网格": "云岩区",
      "日期": "3月",
      "呼入总量": 15,
      "一次接听量": 1,
      "一次接听率": 6.67,
      "回拨次数": 0,
      "真实接听率": 6.67,
      "真实未接通次数": 14
    },
    {
      "姓名": "/",
      "装维账号": "18302508486",
      "网格": "云岩区",
      "日期": "3月",
      "呼入总量": 35,
      "一次接听量": 9,
      "一次接听率": 25.71,
      "回拨次数": 6,
      "真实接听率": 42.86,
      "真实未接通次数": 20
    }
  ],
  "贵阳-白云区": [
    {
      "姓名": "李昌棚",
      "装维账号": "18212026041",
      "网格": "白云区同心社区网格",
      "日期": "3月",
      "呼入总量": 88,
      "一次接听量": 50,
      "一次接听率": 56.82,
      "回拨次数": 5,
      "真实接听率": 62.5,
      "真实未接通次数": 33
    },
    {
      "姓名": "刘涛",
      "装维账号": "18275272996",
      "网格": "白云区同心社区网格",
      "日期": "3月",
      "呼入总量": 482,
      "一次接听量": 14,
      "一次接听率": 2.9,
      "回拨次数": 30,
      "真实接听率": 9.13,
      "真实未接通次数": 438
    },
    {
      "姓名": "/",
      "装维账号": "18275290200",
      "网格": "白云区",
      "日期": "3月",
      "呼入总量": 104,
      "一次接听量": 44,
      "一次接听率": 42.31,
      "回拨次数": 19,
      "真实接听率": 60.58,
      "真实未接通次数": 41
    },
    {
      "姓名": "/",
      "装维账号": "18302508305",
      "网格": "白云区",
      "日期": "3月",
      "呼入总量": 51,
      "一次接听量": 14,
      "一次接听率": 27.45,
      "回拨次数": 17,
      "真实接听率": 60.78,
      "真实未接通次数": 20
    },
    {
      "姓名": "/",
      "装维账号": "18302508541",
      "网格": "白云区",
      "日期": "3月",
      "呼入总量": 65,
      "一次接听量": 10,
      "一次接听率": 15.38,
      "回拨次数": 9,
      "真实接听率": 29.23,
      "真实未接通次数": 46
    }
  ],
  "贵阳-乌当区": [
    {
      "姓名": "/",
      "装维账号": "18275370410",
      "网格": "乌当区",
      "日期": "3月",
      "呼入总量": 35,
      "一次接听量": 14,
      "一次接听率": 40.0,
      "回拨次数": 7,
      "真实接听率": 60.0,
      "真实未接通次数": 14
    },
    {
      "姓名": "/",
      "装维账号": "18300897504",
      "网格": "乌当区",
      "日期": "3月",
      "呼入总量": 11,
      "一次接听量": 4,
      "一次接听率": 36.36,
      "回拨次数": 2,
      "真实接听率": 54.55,
      "真实未接通次数": 5
    },
    {
      "姓名": "肖功清",
      "装维账号": "18302508402",
      "网格": "振兴社区网格",
      "日期": "3月",
      "呼入总量": 314,
      "一次接听量": 81,
      "一次接听率": 25.8,
      "回拨次数": 86,
      "真实接听率": 53.18,
      "真实未接通次数": 147
    },
    {
      "姓名": "陈东浩",
      "装维账号": "18302565045",
      "网格": "先锋社区网格",
      "日期": "3月",
      "呼入总量": 22,
      "一次接听量": 8,
      "一次接听率": 36.36,
      "回拨次数": 4,
      "真实接听率": 54.55,
      "真实未接通次数": 10
    }
  ],
  "贵阳-观山湖区": [
    {
      "姓名": "/",
      "装维账号": "18275399192",
      "网格": "观山湖区",
      "日期": "3月",
      "呼入总量": 4,
      "一次接听量": 1,
      "一次接听率": 25.0,
      "回拨次数": 0,
      "真实接听率": 25.0,
      "真实未接通次数": 3
    },
    {
      "姓名": "/",
      "装维账号": "18285164816",
      "网格": "观山湖区",
      "日期": "3月",
      "呼入总量": 48,
      "一次接听量": 21,
      "一次接听率": 43.75,
      "回拨次数": 12,
      "真实接听率": 68.75,
      "真实未接通次数": 15
    },
    {
      "姓名": "/",
      "装维账号": "18302508271",
      "网格": "观山湖区",
      "日期": "3月",
      "呼入总量": 45,
      "一次接听量": 13,
      "一次接听率": 28.89,
      "回拨次数": 17,
      "真实接听率": 66.67,
      "真实未接通次数": 15
    },
    {
      "姓名": "/",
      "装维账号": "18302508382",
      "网格": "观山湖区",
      "日期": "3月",
      "呼入总量": 60,
      "一次接听量": 32,
      "一次接听率": 53.33,
      "回拨次数": 9,
      "真实接听率": 68.33,
      "真实未接通次数": 19
    },
    {
      "姓名": "/",
      "装维账号": "18302508441",
      "网格": "观山湖区",
      "日期": "3月",
      "呼入总量": 2,
      "一次接听量": 1,
      "一次接听率": 50.0,
      "回拨次数": 0,
      "真实接听率": 50.0,
      "真实未接通次数": 1
    },
    {
      "姓名": "/",
      "装维账号": "18302508443",
      "网格": "观山湖区",
      "日期": "3月",
      "呼入总量": 33,
      "一次接听量": 9,
      "一次接听率": 27.27,
      "回拨次数": 12,
      "真实接听率": 63.64,
      "真实未接通次数": 12
    },
    {
      "姓名": "/",
      "装维账号": "18302508452",
      "网格": "观山湖区",
      "日期": "3月",
      "呼入总量": 100,
      "一次接听量": 27,
      "一次接听率": 27.0,
      "回拨次数": 41,
      "真实接听率": 68.0,
      "真实未接通次数": 32
    },
    {
      "姓名": "/",
      "装维账号": "18302508457",
      "网格": "观山湖区",
      "日期": "3月",
      "呼入总量": 25,
      "一次接听量": 12,
      "一次接听率": 48.0,
      "回拨次数": 0,
      "真实接听率": 48.0,
      "真实未接通次数": 13
    },
    {
      "姓名": "/",
      "装维账号": "18302508753",
      "网格": "观山湖区",
      "日期": "3月",
      "呼入总量": 19,
      "一次接听量": 11,
      "一次接听率": 57.89,
      "回拨次数": 0,
      "真实接听率": 57.89,
      "真实未接通次数": 8
    },
    {
      "姓名": "/",
      "装维账号": "18302508861",
      "网格": "观山湖区",
      "日期": "3月",
      "呼入总量": 12,
      "一次接听量": 5,
      "一次接听率": 41.67,
      "回拨次数": 2,
      "真实接听率": 58.33,
      "真实未接通次数": 5
    },
    {
      "姓名": "/",
      "装维账号": "18302546851",
      "网格": "观山湖区",
      "日期": "3月",
      "呼入总量": 5,
      "一次接听量": 1,
      "一次接听率": 20.0,
      "回拨次数": 0,
      "真实接听率": 20.0,
      "真实未接通次数": 4
    },
    {
      "姓名": "/",
      "装维账号": "18798751364",
      "网格": "观山湖区",
      "日期": "3月",
      "呼入总量": 24,
      "一次接听量": 7,
      "一次接听率": 29.17,
      "回拨次数": 7,
      "真实接听率": 58.33,
      "真实未接通次数": 10
    }
  ],
  "贵阳-花溪区": [
    {
      "姓名": "姜玉学",
      "装维账号": "18285031041",
      "网格": "溪中社区网格",
      "日期": "3月",
      "呼入总量": 9,
      "一次接听量": 2,
      "一次接听率": 22.22,
      "回拨次数": 0,
      "真实接听率": 22.22,
      "真实未接通次数": 7
    },
    {
      "姓名": "邱坤",
      "装维账号": "18302508608",
      "网格": "溪北社区网格",
      "日期": "3月",
      "呼入总量": 59,
      "一次接听量": 24,
      "一次接听率": 40.68,
      "回拨次数": 12,
      "真实接听率": 61.02,
      "真实未接通次数": 23
    },
    {
      "姓名": "赵益波",
      "装维账号": "18302542071",
      "网格": "溪北社区网格",
      "日期": "3月",
      "呼入总量": 26,
      "一次接听量": 5,
      "一次接听率": 19.23,
      "回拨次数": 0,
      "真实接听率": 19.23,
      "真实未接通次数": 21
    }
  ],
  "贵阳-小河区": [
    {
      "姓名": "/",
      "装维账号": "18302508302",
      "网格": "小河区",
      "日期": "3月",
      "呼入总量": 9,
      "一次接听量": 5,
      "一次接听率": 55.56,
      "回拨次数": 0,
      "真实接听率": 55.56,
      "真实未接通次数": 4
    },
    {
      "姓名": "/",
      "装维账号": "18302547665",
      "网格": "小河区",
      "日期": "3月",
      "呼入总量": 5,
      "一次接听量": 3,
      "一次接听率": 60.0,
      "回拨次数": 0,
      "真实接听率": 60.0,
      "真实未接通次数": 2
    }
  ],
  "铜仁-思南县": [
    {
      "姓名": "/",
      "装维账号": "13595664965",
      "网格": "思南县",
      "日期": "3月",
      "呼入总量": 5,
      "一次接听量": 2,
      "一次接听率": 40.0,
      "回拨次数": 0,
      "真实接听率": 40.0,
      "真实未接通次数": 3
    },
    {
      "姓名": "/",
      "装维账号": "13595674484",
      "网格": "思南县",
      "日期": "3月",
      "呼入总量": 10,
      "一次接听量": 3,
      "一次接听率": 30.0,
      "回拨次数": 2,
      "真实接听率": 50.0,
      "真实未接通次数": 5
    },
    {
      "姓名": "/",
      "装维账号": "13595678560",
      "网格": "思南县",
      "日期": "3月",
      "呼入总量": 10,
      "一次接听量": 5,
      "一次接听率": 50.0,
      "回拨次数": 0,
      "真实接听率": 50.0,
      "真实未接通次数": 5
    },
    {
      "姓名": "/",
      "装维账号": "13885694053",
      "网格": "思南县",
      "日期": "3月",
      "呼入总量": 14,
      "一次接听量": 1,
      "一次接听率": 7.14,
      "回拨次数": 2,
      "真实接听率": 21.43,
      "真实未接通次数": 11
    },
    {
      "姓名": "/",
      "装维账号": "15286407650",
      "网格": "思南县",
      "日期": "3月",
      "呼入总量": 5,
      "一次接听量": 2,
      "一次接听率": 40.0,
      "回拨次数": 0,
      "真实接听率": 40.0,
      "真实未接通次数": 3
    },
    {
      "姓名": "/",
      "装维账号": "15718564905",
      "网格": "思南县",
      "日期": "3月",
      "呼入总量": 3,
      "一次接听量": 2,
      "一次接听率": 66.67,
      "回拨次数": 0,
      "真实接听率": 66.67,
      "真实未接通次数": 1
    },
    {
      "姓名": "/",
      "装维账号": "17285603213",
      "网格": "思南县",
      "日期": "3月",
      "呼入总量": 11,
      "一次接听量": 2,
      "一次接听率": 18.18,
      "回拨次数": 0,
      "真实接听率": 18.18,
      "真实未接通次数": 9
    },
    {
      "姓名": "/",
      "装维账号": "18286682067",
      "网格": "思南县",
      "日期": "3月",
      "呼入总量": 3,
      "一次接听量": 2,
      "一次接听率": 66.67,
      "回拨次数": 0,
      "真实接听率": 66.67,
      "真实未接通次数": 1
    },
    {
      "姓名": "/",
      "装维账号": "18286683290",
      "网格": "思南县",
      "日期": "3月",
      "呼入总量": 11,
      "一次接听量": 1,
      "一次接听率": 9.09,
      "回拨次数": 0,
      "真实接听率": 9.09,
      "真实未接通次数": 10
    },
    {
      "姓名": "/",
      "装维账号": "18311713055",
      "网格": "思南县",
      "日期": "3月",
      "呼入总量": 20,
      "一次接听量": 1,
      "一次接听率": 5.0,
      "回拨次数": 8,
      "真实接听率": 45.0,
      "真实未接通次数": 11
    },
    {
      "姓名": "/",
      "装维账号": "18311759897",
      "网格": "思南县",
      "日期": "3月",
      "呼入总量": 10,
      "一次接听量": 1,
      "一次接听率": 10.0,
      "回拨次数": 5,
      "真实接听率": 60.0,
      "真实未接通次数": 4
    },
    {
      "姓名": "/",
      "装维账号": "18311772655",
      "网格": "思南县",
      "日期": "3月",
      "呼入总量": 22,
      "一次接听量": 10,
      "一次接听率": 45.45,
      "回拨次数": 2,
      "真实接听率": 54.55,
      "真实未接通次数": 10
    },
    {
      "姓名": "/",
      "装维账号": "18311776163",
      "网格": "思南县",
      "日期": "3月",
      "呼入总量": 8,
      "一次接听量": 0,
      "一次接听率": 0.0,
      "回拨次数": 4,
      "真实接听率": 50.0,
      "真实未接通次数": 4
    },
    {
      "姓名": "/",
      "装维账号": "18311851730",
      "网格": "思南县",
      "日期": "3月",
      "呼入总量": 2,
      "一次接听量": 1,
      "一次接听率": 50.0,
      "回拨次数": 0,
      "真实接听率": 50.0,
      "真实未接通次数": 1
    },
    {
      "姓名": "/",
      "装维账号": "18385883815",
      "网格": "思南县",
      "日期": "3月",
      "呼入总量": 11,
      "一次接听量": 7,
      "一次接听率": 63.64,
      "回拨次数": 0,
      "真实接听率": 63.64,
      "真实未接通次数": 4
    },
    {
      "姓名": "/",
      "装维账号": "18385922874",
      "网格": "思南县",
      "日期": "3月",
      "呼入总量": 5,
      "一次接听量": 3,
      "一次接听率": 60.0,
      "回拨次数": 0,
      "真实接听率": 60.0,
      "真实未接通次数": 2
    },
    {
      "姓名": "/",
      "装维账号": "18385967101",
      "网格": "思南县",
      "日期": "3月",
      "呼入总量": 3,
      "一次接听量": 1,
      "一次接听率": 33.33,
      "回拨次数": 0,
      "真实接听率": 33.33,
      "真实未接通次数": 2
    },
    {
      "姓名": "/",
      "装维账号": "18885638144",
      "网格": "思南县",
      "日期": "3月",
      "呼入总量": 3,
      "一次接听量": 2,
      "一次接听率": 66.67,
      "回拨次数": 0,
      "真实接听率": 66.67,
      "真实未接通次数": 1
    }
  ],
  "铜仁-德江县": [
    {
      "姓名": "/",
      "装维账号": "13618563265",
      "网格": "德江县",
      "日期": "3月",
      "呼入总量": 5,
      "一次接听量": 3,
      "一次接听率": 60.0,
      "回拨次数": 0,
      "真实接听率": 60.0,
      "真实未接通次数": 2
    },
    {
      "姓名": "/",
      "装维账号": "15186006064",
      "网格": "德江县",
      "日期": "3月",
      "呼入总量": 9,
      "一次接听量": 3,
      "一次接听率": 33.33,
      "回拨次数": 3,
      "真实接听率": 66.67,
      "真实未接通次数": 3
    },
    {
      "姓名": "/",
      "装维账号": "17285662139",
      "网格": "德江县",
      "日期": "3月",
      "呼入总量": 2,
      "一次接听量": 1,
      "一次接听率": 50.0,
      "回拨次数": 0,
      "真实接听率": 50.0,
      "真实未接通次数": 1
    },
    {
      "姓名": "/",
      "装维账号": "17285666015",
      "网格": "德江县",
      "日期": "3月",
      "呼入总量": 2,
      "一次接听量": 1,
      "一次接听率": 50.0,
      "回拨次数": 0,
      "真实接听率": 50.0,
      "真实未接通次数": 1
    },
    {
      "姓名": "/",
      "装维账号": "18385895326",
      "网格": "德江县",
      "日期": "3月",
      "呼入总量": 15,
      "一次接听量": 7,
      "一次接听率": 46.67,
      "回拨次数": 2,
      "真实接听率": 60.0,
      "真实未接通次数": 6
    },
    {
      "姓名": "/",
      "装维账号": "18885607843",
      "网格": "德江县",
      "日期": "3月",
      "呼入总量": 29,
      "一次接听量": 13,
      "一次接听率": 44.83,
      "回拨次数": 6,
      "真实接听率": 65.52,
      "真实未接通次数": 10
    },
    {
      "姓名": "/",
      "装维账号": "18885634530",
      "网格": "德江县",
      "日期": "3月",
      "呼入总量": 16,
      "一次接听量": 6,
      "一次接听率": 37.5,
      "回拨次数": 2,
      "真实接听率": 50.0,
      "真实未接通次数": 8
    },
    {
      "姓名": "/",
      "装维账号": "18885640757",
      "网格": "德江县",
      "日期": "3月",
      "呼入总量": 11,
      "一次接听量": 7,
      "一次接听率": 63.64,
      "回拨次数": 0,
      "真实接听率": 63.64,
      "真实未接通次数": 4
    },
    {
      "姓名": "/",
      "装维账号": "18885652151",
      "网格": "德江县",
      "日期": "3月",
      "呼入总量": 4,
      "一次接听量": 2,
      "一次接听率": 50.0,
      "回拨次数": 0,
      "真实接听率": 50.0,
      "真实未接通次数": 2
    }
  ],
  "铜仁-松桃县": [
    {
      "姓名": "/",
      "装维账号": "13638118655",
      "网格": "松桃县",
      "日期": "3月",
      "呼入总量": 8,
      "一次接听量": 3,
      "一次接听率": 37.5,
      "回拨次数": 2,
      "真实接听率": 62.5,
      "真实未接通次数": 3
    },
    {
      "姓名": "/",
      "装维账号": "15286744520",
      "网格": "松桃县",
      "日期": "3月",
      "呼入总量": 12,
      "一次接听量": 6,
      "一次接听率": 50.0,
      "回拨次数": 0,
      "真实接听率": 50.0,
      "真实未接通次数": 6
    },
    {
      "姓名": "/",
      "装维账号": "15286795112",
      "网格": "松桃县",
      "日期": "3月",
      "呼入总量": 10,
      "一次接听量": 1,
      "一次接听率": 10.0,
      "回拨次数": 4,
      "真实接听率": 50.0,
      "真实未接通次数": 5
    },
    {
      "姓名": "/",
      "装维账号": "15761349344",
      "网格": "松桃县",
      "日期": "3月",
      "呼入总量": 9,
      "一次接听量": 3,
      "一次接听率": 33.33,
      "回拨次数": 2,
      "真实接听率": 55.56,
      "真实未接通次数": 4
    },
    {
      "姓名": "/",
      "装维账号": "17285667113",
      "网格": "松桃县",
      "日期": "3月",
      "呼入总量": 17,
      "一次接听量": 3,
      "一次接听率": 17.65,
      "回拨次数": 6,
      "真实接听率": 52.94,
      "真实未接通次数": 8
    },
    {
      "姓名": "/",
      "装维账号": "17285668112",
      "网格": "松桃县",
      "日期": "3月",
      "呼入总量": 3,
      "一次接听量": 1,
      "一次接听率": 33.33,
      "回拨次数": 0,
      "真实接听率": 33.33,
      "真实未接通次数": 2
    },
    {
      "姓名": "/",
      "装维账号": "17285668763",
      "网格": "松桃县",
      "日期": "3月",
      "呼入总量": 7,
      "一次接听量": 4,
      "一次接听率": 57.14,
      "回拨次数": 0,
      "真实接听率": 57.14,
      "真实未接通次数": 3
    },
    {
      "姓名": "/",
      "装维账号": "17285685977",
      "网格": "松桃县",
      "日期": "3月",
      "呼入总量": 5,
      "一次接听量": 3,
      "一次接听率": 60.0,
      "回拨次数": 0,
      "真实接听率": 60.0,
      "真实未接通次数": 2
    },
    {
      "姓名": "/",
      "装维账号": "18311727858",
      "网格": "松桃县",
      "日期": "3月",
      "呼入总量": 5,
      "一次接听量": 1,
      "一次接听率": 20.0,
      "回拨次数": 0,
      "真实接听率": 20.0,
      "真实未接通次数": 4
    },
    {
      "姓名": "/",
      "装维账号": "18385875291",
      "网格": "松桃县",
      "日期": "3月",
      "呼入总量": 29,
      "一次接听量": 10,
      "一次接听率": 34.48,
      "回拨次数": 0,
      "真实接听率": 34.48,
      "真实未接通次数": 19
    },
    {
      "姓名": "/",
      "装维账号": "18885679420",
      "网格": "松桃县",
      "日期": "3月",
      "呼入总量": 12,
      "一次接听量": 1,
      "一次接听率": 8.33,
      "回拨次数": 0,
      "真实接听率": 8.33,
      "真实未接通次数": 11
    },
    {
      "姓名": "/",
      "装维账号": "19885160706",
      "网格": "松桃县",
      "日期": "3月",
      "呼入总量": 5,
      "一次接听量": 3,
      "一次接听率": 60.0,
      "回拨次数": 0,
      "真实接听率": 60.0,
      "真实未接通次数": 2
    },
    {
      "姓名": "/",
      "装维账号": "19885175110",
      "网格": "松桃县",
      "日期": "3月",
      "呼入总量": 14,
      "一次接听量": 2,
      "一次接听率": 14.29,
      "回拨次数": 2,
      "真实接听率": 28.57,
      "真实未接通次数": 10
    }
  ],
  "铜仁-江口县": [
    {
      "姓名": "/",
      "装维账号": "13638560420",
      "网格": "江口县",
      "日期": "3月",
      "呼入总量": 23,
      "一次接听量": 9,
      "一次接听率": 39.13,
      "回拨次数": 2,
      "真实接听率": 47.83,
      "真实未接通次数": 12
    },
    {
      "姓名": "/",
      "装维账号": "13648564094",
      "网格": "江口县",
      "日期": "3月",
      "呼入总量": 2,
      "一次接听量": 1,
      "一次接听率": 50.0,
      "回拨次数": 0,
      "真实接听率": 50.0,
      "真实未接通次数": 1
    },
    {
      "姓名": "/",
      "装维账号": "13648567475",
      "网格": "江口县",
      "日期": "3月",
      "呼入总量": 22,
      "一次接听量": 9,
      "一次接听率": 40.91,
      "回拨次数": 3,
      "真实接听率": 54.55,
      "真实未接通次数": 10
    },
    {
      "姓名": "/",
      "装维账号": "13765604197",
      "网格": "江口县",
      "日期": "3月",
      "呼入总量": 52,
      "一次接听量": 24,
      "一次接听率": 46.15,
      "回拨次数": 9,
      "真实接听率": 63.46,
      "真实未接通次数": 19
    },
    {
      "姓名": "/",
      "装维账号": "19885158391",
      "网格": "江口县",
      "日期": "3月",
      "呼入总量": 19,
      "一次接听量": 8,
      "一次接听率": 42.11,
      "回拨次数": 0,
      "真实接听率": 42.11,
      "真实未接通次数": 11
    }
  ],
  "铜仁-万山区": [
    {
      "姓名": "张敏（家客）",
      "装维账号": "13721569663",
      "网格": "万山区城区维护班组3（铁通谢桥3组)",
      "日期": "3月",
      "呼入总量": 70,
      "一次接听量": 28,
      "一次接听率": 40.0,
      "回拨次数": 17,
      "真实接听率": 64.29,
      "真实未接通次数": 25
    },
    {
      "姓名": "/",
      "装维账号": "18208563303",
      "网格": "万山区",
      "日期": "3月",
      "呼入总量": 139,
      "一次接听量": 52,
      "一次接听率": 37.41,
      "回拨次数": 28,
      "真实接听率": 57.55,
      "真实未接通次数": 59
    }
  ],
  "铜仁-印江县": [
    {
      "姓名": "/",
      "装维账号": "13765651824",
      "网格": "印江县",
      "日期": "3月",
      "呼入总量": 6,
      "一次接听量": 4,
      "一次接听率": 66.67,
      "回拨次数": 0,
      "真实接听率": 66.67,
      "真实未接通次数": 2
    },
    {
      "姓名": "/",
      "装维账号": "13765673207",
      "网格": "印江县",
      "日期": "3月",
      "呼入总量": 5,
      "一次接听量": 3,
      "一次接听率": 60.0,
      "回拨次数": 0,
      "真实接听率": 60.0,
      "真实未接通次数": 2
    },
    {
      "姓名": "/",
      "装维账号": "15117741802",
      "网格": "印江县",
      "日期": "3月",
      "呼入总量": 11,
      "一次接听量": 7,
      "一次接听率": 63.64,
      "回拨次数": 0,
      "真实接听率": 63.64,
      "真实未接通次数": 4
    },
    {
      "姓名": "/",
      "装维账号": "15870189614",
      "网格": "印江县",
      "日期": "3月",
      "呼入总量": 9,
      "一次接听量": 3,
      "一次接听率": 33.33,
      "回拨次数": 2,
      "真实接听率": 55.56,
      "真实未接通次数": 4
    },
    {
      "姓名": "/",
      "装维账号": "17285668306",
      "网格": "印江县",
      "日期": "3月",
      "呼入总量": 6,
      "一次接听量": 3,
      "一次接听率": 50.0,
      "回拨次数": 0,
      "真实接听率": 50.0,
      "真实未接通次数": 3
    },
    {
      "姓名": "/",
      "装维账号": "18311742327",
      "网格": "印江县",
      "日期": "3月",
      "呼入总量": 22,
      "一次接听量": 14,
      "一次接听率": 63.64,
      "回拨次数": 0,
      "真实接听率": 63.64,
      "真实未接通次数": 8
    },
    {
      "姓名": "/",
      "装维账号": "18385950893",
      "网格": "印江县",
      "日期": "3月",
      "呼入总量": 13,
      "一次接听量": 3,
      "一次接听率": 23.08,
      "回拨次数": 0,
      "真实接听率": 23.08,
      "真实未接通次数": 10
    },
    {
      "姓名": "/",
      "装维账号": "18744861871",
      "网格": "印江县",
      "日期": "3月",
      "呼入总量": 14,
      "一次接听量": 5,
      "一次接听率": 35.71,
      "回拨次数": 2,
      "真实接听率": 50.0,
      "真实未接通次数": 7
    },
    {
      "姓名": "/",
      "装维账号": "18785618505",
      "网格": "印江县",
      "日期": "3月",
      "呼入总量": 14,
      "一次接听量": 1,
      "一次接听率": 7.14,
      "回拨次数": 6,
      "真实接听率": 50.0,
      "真实未接通次数": 7
    }
  ],
  "铜仁-碧江区": [
    {
      "姓名": "万凯（家客）",
      "装维账号": "13765653545",
      "网格": "碧江区乡镇驻点班组10（铁通-川硐网格)",
      "日期": "3月",
      "呼入总量": 10,
      "一次接听量": 3,
      "一次接听率": 30.0,
      "回拨次数": 0,
      "真实接听率": 30.0,
      "真实未接通次数": 7
    },
    {
      "姓名": "邓钟（家客）",
      "装维账号": "13765672533",
      "网格": "碧江区城区驻点7班组（铁通-河西网格）",
      "日期": "3月",
      "呼入总量": 109,
      "一次接听量": 41,
      "一次接听率": 37.61,
      "回拨次数": 24,
      "真实接听率": 59.63,
      "真实未接通次数": 44
    },
    {
      "姓名": "吴文怡（家客）",
      "装维账号": "15761389419",
      "网格": "碧江区城区驻点班组13（铁通-锦江网格)",
      "日期": "3月",
      "呼入总量": 34,
      "一次接听量": 11,
      "一次接听率": 32.35,
      "回拨次数": 11,
      "真实接听率": 64.71,
      "真实未接通次数": 12
    },
    {
      "姓名": "/",
      "装维账号": "19886813090",
      "网格": "碧江区",
      "日期": "3月",
      "呼入总量": 18,
      "一次接听量": 7,
      "一次接听率": 38.89,
      "回拨次数": 5,
      "真实接听率": 66.67,
      "真实未接通次数": 6
    }
  ],
  "铜仁-石阡县": [
    {
      "姓名": "/",
      "装维账号": "13765672693",
      "网格": "石阡县",
      "日期": "3月",
      "呼入总量": 3,
      "一次接听量": 0,
      "一次接听率": 0.0,
      "回拨次数": 1,
      "真实接听率": 33.33,
      "真实未接通次数": 2
    },
    {
      "姓名": "/",
      "装维账号": "15117736978",
      "网格": "石阡县",
      "日期": "3月",
      "呼入总量": 2,
      "一次接听量": 1,
      "一次接听率": 50.0,
      "回拨次数": 0,
      "真实接听率": 50.0,
      "真实未接通次数": 1
    },
    {
      "姓名": "/",
      "装维账号": "15186003688",
      "网格": "石阡县",
      "日期": "3月",
      "呼入总量": 9,
      "一次接听量": 4,
      "一次接听率": 44.44,
      "回拨次数": 0,
      "真实接听率": 44.44,
      "真实未接通次数": 5
    },
    {
      "姓名": "/",
      "装维账号": "18286633123",
      "网格": "石阡县",
      "日期": "3月",
      "呼入总量": 16,
      "一次接听量": 2,
      "一次接听率": 12.5,
      "回拨次数": 3,
      "真实接听率": 31.25,
      "真实未接通次数": 11
    },
    {
      "姓名": "/",
      "装维账号": "18708609123",
      "网格": "石阡县",
      "日期": "3月",
      "呼入总量": 26,
      "一次接听量": 8,
      "一次接听率": 30.77,
      "回拨次数": 7,
      "真实接听率": 57.69,
      "真实未接通次数": 11
    },
    {
      "姓名": "/",
      "装维账号": "18722939123",
      "网格": "石阡县",
      "日期": "3月",
      "呼入总量": 14,
      "一次接听量": 1,
      "一次接听率": 7.14,
      "回拨次数": 0,
      "真实接听率": 7.14,
      "真实未接通次数": 13
    },
    {
      "姓名": "/",
      "装维账号": "18885679288",
      "网格": "石阡县",
      "日期": "3月",
      "呼入总量": 18,
      "一次接听量": 7,
      "一次接听率": 38.89,
      "回拨次数": 0,
      "真实接听率": 38.89,
      "真实未接通次数": 11
    }
  ],
  "铜仁-沿河县": [
    {
      "姓名": "/",
      "装维账号": "15285400500",
      "网格": "沿河县",
      "日期": "3月",
      "呼入总量": 5,
      "一次接听量": 0,
      "一次接听率": 0.0,
      "回拨次数": 1,
      "真实接听率": 20.0,
      "真实未接通次数": 4
    },
    {
      "姓名": "/",
      "装维账号": "17285664500",
      "网格": "沿河县",
      "日期": "3月",
      "呼入总量": 32,
      "一次接听量": 14,
      "一次接听率": 43.75,
      "回拨次数": 1,
      "真实接听率": 46.88,
      "真实未接通次数": 17
    },
    {
      "姓名": "/",
      "装维账号": "17285669700",
      "网格": "沿河县",
      "日期": "3月",
      "呼入总量": 19,
      "一次接听量": 1,
      "一次接听率": 5.26,
      "回拨次数": 0,
      "真实接听率": 5.26,
      "真实未接通次数": 18
    },
    {
      "姓名": "/",
      "装维账号": "17285687400",
      "网格": "沿河县",
      "日期": "3月",
      "呼入总量": 2,
      "一次接听量": 1,
      "一次接听率": 50.0,
      "回拨次数": 0,
      "真实接听率": 50.0,
      "真实未接通次数": 1
    },
    {
      "姓名": "/",
      "装维账号": "17285691500",
      "网格": "沿河县",
      "日期": "3月",
      "呼入总量": 9,
      "一次接听量": 6,
      "一次接听率": 66.67,
      "回拨次数": 0,
      "真实接听率": 66.67,
      "真实未接通次数": 3
    },
    {
      "姓名": "/",
      "装维账号": "18311723400",
      "网格": "沿河县",
      "日期": "3月",
      "呼入总量": 6,
      "一次接听量": 1,
      "一次接听率": 16.67,
      "回拨次数": 1,
      "真实接听率": 33.33,
      "真实未接通次数": 4
    },
    {
      "姓名": "/",
      "装维账号": "19886836800",
      "网格": "沿河县",
      "日期": "3月",
      "呼入总量": 15,
      "一次接听量": 1,
      "一次接听率": 6.67,
      "回拨次数": 7,
      "真实接听率": 53.33,
      "真实未接通次数": 7
    }
  ],
  "六盘水-水城县": [
    {
      "姓名": "/",
      "装维账号": "13639156599",
      "网格": "水城县",
      "日期": "3月",
      "呼入总量": 17,
      "一次接听量": 10,
      "一次接听率": 58.82,
      "回拨次数": 0,
      "真实接听率": 58.82,
      "真实未接通次数": 7
    },
    {
      "姓名": "赵胜车",
      "装维账号": "14785348560",
      "网格": "水城县城区代维驻点集客家客维护组1",
      "日期": "3月",
      "呼入总量": 123,
      "一次接听量": 51,
      "一次接听率": 41.46,
      "回拨次数": 26,
      "真实接听率": 62.6,
      "真实未接通次数": 46
    },
    {
      "姓名": "黄富印",
      "装维账号": "18786713185",
      "网格": "水城县城区代维驻点集客家客维护组1",
      "日期": "3月",
      "呼入总量": 77,
      "一次接听量": 37,
      "一次接听率": 48.05,
      "回拨次数": 11,
      "真实接听率": 62.34,
      "真实未接通次数": 29
    },
    {
      "姓名": "花嘎合作方赵思维",
      "装维账号": "18885897890",
      "网格": "水城县城区代维驻点集客家客维护组1",
      "日期": "3月",
      "呼入总量": 81,
      "一次接听量": 17,
      "一次接听率": 20.99,
      "回拨次数": 25,
      "真实接听率": 51.85,
      "真实未接通次数": 39
    },
    {
      "姓名": "都格合作方黄信龙",
      "装维账号": "18886887786",
      "网格": "水城县城区代维驻点集客家客维护组1",
      "日期": "3月",
      "呼入总量": 465,
      "一次接听量": 91,
      "一次接听率": 19.57,
      "回拨次数": 195,
      "真实接听率": 61.51,
      "真实未接通次数": 179
    }
  ],
  "六盘水-六枝县": [
    {
      "姓名": "/",
      "装维账号": "13708583266",
      "网格": "六枝县",
      "日期": "3月",
      "呼入总量": 27,
      "一次接听量": 13,
      "一次接听率": 48.15,
      "回拨次数": 0,
      "真实接听率": 48.15,
      "真实未接通次数": 14
    },
    {
      "姓名": "/",
      "装维账号": "14785348996",
      "网格": "六枝县",
      "日期": "3月",
      "呼入总量": 194,
      "一次接听量": 82,
      "一次接听率": 42.27,
      "回拨次数": 32,
      "真实接听率": 58.76,
      "真实未接通次数": 80
    },
    {
      "姓名": "/",
      "装维账号": "18083696091",
      "网格": "六枝县",
      "日期": "3月",
      "呼入总量": 19,
      "一次接听量": 10,
      "一次接听率": 52.63,
      "回拨次数": 2,
      "真实接听率": 63.16,
      "真实未接通次数": 7
    }
  ],
  "六盘水-盘州": [
    {
      "姓名": "鸡场坪网格_合作方_袁鹏",
      "装维账号": "14785345682",
      "网格": "盘县城区代维驻点集客家客维护组4",
      "日期": "3月",
      "呼入总量": 16,
      "一次接听量": 4,
      "一次接听率": 25.0,
      "回拨次数": 6,
      "真实接听率": 62.5,
      "真实未接通次数": 6
    },
    {
      "姓名": "/",
      "装维账号": "18216660878",
      "网格": "盘州",
      "日期": "3月",
      "呼入总量": 158,
      "一次接听量": 4,
      "一次接听率": 2.53,
      "回拨次数": 6,
      "真实接听率": 6.33,
      "真实未接通次数": 148
    }
  ],
  "六盘水-钟山区": [
    {
      "姓名": "/",
      "装维账号": "14785349156",
      "网格": "钟山区",
      "日期": "3月",
      "呼入总量": 26,
      "一次接听量": 14,
      "一次接听率": 53.85,
      "回拨次数": 0,
      "真实接听率": 53.85,
      "真实未接通次数": 12
    },
    {
      "姓名": "/",
      "装维账号": "18285817401",
      "网格": "钟山区",
      "日期": "3月",
      "呼入总量": 11,
      "一次接听量": 6,
      "一次接听率": 54.55,
      "回拨次数": 0,
      "真实接听率": 54.55,
      "真实未接通次数": 5
    }
  ],
  "黔东南-台江县": [
    {
      "姓名": "/",
      "装维账号": "13765573940",
      "网格": "台江县",
      "日期": "3月",
      "呼入总量": 3,
      "一次接听量": 1,
      "一次接听率": 33.33,
      "回拨次数": 0,
      "真实接听率": 33.33,
      "真实未接通次数": 2
    },
    {
      "姓名": "/",
      "装维账号": "15772595925",
      "网格": "台江县",
      "日期": "3月",
      "呼入总量": 23,
      "一次接听量": 11,
      "一次接听率": 47.83,
      "回拨次数": 5,
      "真实接听率": 69.57,
      "真实未接通次数": 7
    }
  ],
  "黔东南-麻江县": [
    {
      "姓名": "/",
      "装维账号": "15121466287",
      "网格": "麻江县",
      "日期": "3月",
      "呼入总量": 27,
      "一次接听量": 18,
      "一次接听率": 66.67,
      "回拨次数": 0,
      "真实接听率": 66.67,
      "真实未接通次数": 9
    },
    {
      "姓名": "/",
      "装维账号": "15772595961",
      "网格": "麻江县",
      "日期": "3月",
      "呼入总量": 12,
      "一次接听量": 3,
      "一次接听率": 25.0,
      "回拨次数": 0,
      "真实接听率": 25.0,
      "真实未接通次数": 9
    },
    {
      "姓名": "/",
      "装维账号": "18308550621",
      "网格": "麻江县",
      "日期": "3月",
      "呼入总量": 3,
      "一次接听量": 2,
      "一次接听率": 66.67,
      "回拨次数": 0,
      "真实接听率": 66.67,
      "真实未接通次数": 1
    }
  ],
  "黔东南-岑巩县": [
    {
      "姓名": "/",
      "装维账号": "15772555242",
      "网格": "岑巩县",
      "日期": "3月",
      "呼入总量": 8,
      "一次接听量": 2,
      "一次接听率": 25.0,
      "回拨次数": 1,
      "真实接听率": 37.5,
      "真实未接通次数": 5
    },
    {
      "姓名": "/",
      "装维账号": "15772595733",
      "网格": "岑巩县",
      "日期": "3月",
      "呼入总量": 121,
      "一次接听量": 42,
      "一次接听率": 34.71,
      "回拨次数": 40,
      "真实接听率": 67.77,
      "真实未接通次数": 39
    }
  ],
  "黔东南-凯里市": [
    {
      "姓名": "程磊",
      "装维账号": "15772556940",
      "网格": "凯里市城区代维驻点集客家客维护组1",
      "日期": "3月",
      "呼入总量": 86,
      "一次接听量": 26,
      "一次接听率": 30.23,
      "回拨次数": 13,
      "真实接听率": 45.35,
      "真实未接通次数": 47
    },
    {
      "姓名": "/",
      "装维账号": "15772564547",
      "网格": "凯里市",
      "日期": "3月",
      "呼入总量": 11,
      "一次接听量": 4,
      "一次接听率": 36.36,
      "回拨次数": 2,
      "真实接听率": 54.55,
      "真实未接通次数": 5
    },
    {
      "姓名": "/",
      "装维账号": "15772578475",
      "网格": "凯里市",
      "日期": "3月",
      "呼入总量": 6,
      "一次接听量": 2,
      "一次接听率": 33.33,
      "回拨次数": 0,
      "真实接听率": 33.33,
      "真实未接通次数": 4
    },
    {
      "姓名": "/",
      "装维账号": "15772594577",
      "网格": "凯里市",
      "日期": "3月",
      "呼入总量": 3,
      "一次接听量": 1,
      "一次接听率": 33.33,
      "回拨次数": 0,
      "真实接听率": 33.33,
      "真实未接通次数": 2
    },
    {
      "姓名": "/",
      "装维账号": "15772594933",
      "网格": "凯里市",
      "日期": "3月",
      "呼入总量": 20,
      "一次接听量": 11,
      "一次接听率": 55.0,
      "回拨次数": 1,
      "真实接听率": 60.0,
      "真实未接通次数": 8
    },
    {
      "姓名": "/",
      "装维账号": "15902552085",
      "网格": "凯里市",
      "日期": "3月",
      "呼入总量": 13,
      "一次接听量": 3,
      "一次接听率": 23.08,
      "回拨次数": 0,
      "真实接听率": 23.08,
      "真实未接通次数": 10
    },
    {
      "姓名": "文晨鑫",
      "装维账号": "18212340442",
      "网格": "凯里市城区代维驻点集客家客维护组3",
      "日期": "3月",
      "呼入总量": 17,
      "一次接听量": 8,
      "一次接听率": 47.06,
      "回拨次数": 1,
      "真实接听率": 52.94,
      "真实未接通次数": 8
    },
    {
      "姓名": "/",
      "装维账号": "18385790248",
      "网格": "凯里市",
      "日期": "3月",
      "呼入总量": 4,
      "一次接听量": 2,
      "一次接听率": 50.0,
      "回拨次数": 0,
      "真实接听率": 50.0,
      "真实未接通次数": 2
    },
    {
      "姓名": "/",
      "装维账号": "19581166879",
      "网格": "凯里市",
      "日期": "3月",
      "呼入总量": 13,
      "一次接听量": 2,
      "一次接听率": 15.38,
      "回拨次数": 0,
      "真实接听率": 15.38,
      "真实未接通次数": 11
    },
    {
      "姓名": "/",
      "装维账号": "19581187277",
      "网格": "凯里市",
      "日期": "3月",
      "呼入总量": 24,
      "一次接听量": 3,
      "一次接听率": 12.5,
      "回拨次数": 2,
      "真实接听率": 20.83,
      "真实未接通次数": 19
    }
  ],
  "黔东南-雷山县": [
    {
      "姓名": "/",
      "装维账号": "15772559649",
      "网格": "雷山县",
      "日期": "3月",
      "呼入总量": 14,
      "一次接听量": 5,
      "一次接听率": 35.71,
      "回拨次数": 3,
      "真实接听率": 57.14,
      "真实未接通次数": 6
    }
  ],
  "黔东南-三穗县": [
    {
      "姓名": "/",
      "装维账号": "15772595519",
      "网格": "三穗县",
      "日期": "3月",
      "呼入总量": 60,
      "一次接听量": 34,
      "一次接听率": 56.67,
      "回拨次数": 3,
      "真实接听率": 61.67,
      "真实未接通次数": 23
    },
    {
      "姓名": "龙世明",
      "装维账号": "15772595593",
      "网格": "三穗县城区代维驻点集客家客维护组1",
      "日期": "3月",
      "呼入总量": 48,
      "一次接听量": 12,
      "一次接听率": 25.0,
      "回拨次数": 0,
      "真实接听率": 25.0,
      "真实未接通次数": 36
    }
  ],
  "黔东南-黎平县": [
    {
      "姓名": "/",
      "装维账号": "15772595573",
      "网格": "黎平县",
      "日期": "3月",
      "呼入总量": 45,
      "一次接听量": 12,
      "一次接听率": 26.67,
      "回拨次数": 4,
      "真实接听率": 35.56,
      "真实未接通次数": 29
    },
    {
      "姓名": "/",
      "装维账号": "18785579003",
      "网格": "黎平县",
      "日期": "3月",
      "呼入总量": 8,
      "一次接听量": 0,
      "一次接听率": 0.0,
      "回拨次数": 2,
      "真实接听率": 25.0,
      "真实未接通次数": 6
    },
    {
      "姓名": "/",
      "装维账号": "19585509422",
      "网格": "黎平县",
      "日期": "3月",
      "呼入总量": 3,
      "一次接听量": 1,
      "一次接听率": 33.33,
      "回拨次数": 0,
      "真实接听率": 33.33,
      "真实未接通次数": 2
    }
  ],
  "黔东南-从江县": [
    {
      "姓名": "/",
      "装维账号": "15772595627",
      "网格": "从江县",
      "日期": "3月",
      "呼入总量": 28,
      "一次接听量": 10,
      "一次接听率": 35.71,
      "回拨次数": 4,
      "真实接听率": 50.0,
      "真实未接通次数": 14
    },
    {
      "姓名": "/",
      "装维账号": "19585500324",
      "网格": "从江县",
      "日期": "3月",
      "呼入总量": 22,
      "一次接听量": 6,
      "一次接听率": 27.27,
      "回拨次数": 4,
      "真实接听率": 45.45,
      "真实未接通次数": 12
    },
    {
      "姓名": "梁佳果2",
      "装维账号": "19585500327",
      "网格": "从江县城区代维驻点集客家客维护组1",
      "日期": "3月",
      "呼入总量": 12,
      "一次接听量": 3,
      "一次接听率": 25.0,
      "回拨次数": 0,
      "真实接听率": 25.0,
      "真实未接通次数": 9
    }
  ],
  "黔东南-丹寨县": [
    {
      "姓名": "/",
      "装维账号": "19808467603",
      "网格": "丹寨县",
      "日期": "3月",
      "呼入总量": 37,
      "一次接听量": 2,
      "一次接听率": 5.41,
      "回拨次数": 0,
      "真实接听率": 5.41,
      "真实未接通次数": 35
    }
  ],
  "毕节-威宁县": [
    {
      "姓名": "/",
      "装维账号": "14728674425",
      "网格": "威宁县",
      "日期": "3月",
      "呼入总量": 15,
      "一次接听量": 10,
      "一次接听率": 66.67,
      "回拨次数": 0,
      "真实接听率": 66.67,
      "真实未接通次数": 5
    },
    {
      "姓名": "/",
      "装维账号": "15086327404",
      "网格": "威宁县",
      "日期": "3月",
      "呼入总量": 64,
      "一次接听量": 14,
      "一次接听率": 21.88,
      "回拨次数": 4,
      "真实接听率": 28.13,
      "真实未接通次数": 46
    },
    {
      "姓名": "/",
      "装维账号": "15117524735",
      "网格": "威宁县",
      "日期": "3月",
      "呼入总量": 34,
      "一次接听量": 0,
      "一次接听率": 0.0,
      "回拨次数": 2,
      "真实接听率": 5.88,
      "真实未接通次数": 32
    },
    {
      "姓名": "/",
      "装维账号": "15934764971",
      "网格": "威宁县",
      "日期": "3月",
      "呼入总量": 42,
      "一次接听量": 13,
      "一次接听率": 30.95,
      "回拨次数": 8,
      "真实接听率": 50.0,
      "真实未接通次数": 21
    },
    {
      "姓名": "/",
      "装维账号": "18334189787",
      "网格": "威宁县",
      "日期": "3月",
      "呼入总量": 14,
      "一次接听量": 7,
      "一次接听率": 50.0,
      "回拨次数": 0,
      "真实接听率": 50.0,
      "真实未接通次数": 7
    },
    {
      "姓名": "/",
      "装维账号": "18886720167",
      "网格": "威宁县",
      "日期": "3月",
      "呼入总量": 5,
      "一次接听量": 2,
      "一次接听率": 40.0,
      "回拨次数": 0,
      "真实接听率": 40.0,
      "真实未接通次数": 3
    },
    {
      "姓名": "/",
      "装维账号": "18886720168",
      "网格": "威宁县",
      "日期": "3月",
      "呼入总量": 27,
      "一次接听量": 4,
      "一次接听率": 14.81,
      "回拨次数": 5,
      "真实接听率": 33.33,
      "真实未接通次数": 18
    },
    {
      "姓名": "/",
      "装维账号": "18886720179",
      "网格": "威宁县",
      "日期": "3月",
      "呼入总量": 5,
      "一次接听量": 3,
      "一次接听率": 60.0,
      "回拨次数": 0,
      "真实接听率": 60.0,
      "真实未接通次数": 2
    },
    {
      "姓名": "/",
      "装维账号": "18886720180",
      "网格": "威宁县",
      "日期": "3月",
      "呼入总量": 4,
      "一次接听量": 2,
      "一次接听率": 50.0,
      "回拨次数": 0,
      "真实接听率": 50.0,
      "真实未接通次数": 2
    },
    {
      "姓名": "/",
      "装维账号": "18886720198",
      "网格": "威宁县",
      "日期": "3月",
      "呼入总量": 17,
      "一次接听量": 5,
      "一次接听率": 29.41,
      "回拨次数": 2,
      "真实接听率": 41.18,
      "真实未接通次数": 10
    },
    {
      "姓名": "/",
      "装维账号": "18886720201",
      "网格": "威宁县",
      "日期": "3月",
      "呼入总量": 3,
      "一次接听量": 2,
      "一次接听率": 66.67,
      "回拨次数": 0,
      "真实接听率": 66.67,
      "真实未接通次数": 1
    },
    {
      "姓名": "/",
      "装维账号": "18886720206",
      "网格": "威宁县",
      "日期": "3月",
      "呼入总量": 15,
      "一次接听量": 4,
      "一次接听率": 26.67,
      "回拨次数": 1,
      "真实接听率": 33.33,
      "真实未接通次数": 10
    },
    {
      "姓名": "/",
      "装维账号": "18886720207",
      "网格": "威宁县",
      "日期": "3月",
      "呼入总量": 5,
      "一次接听量": 2,
      "一次接听率": 40.0,
      "回拨次数": 0,
      "真实接听率": 40.0,
      "真实未接通次数": 3
    },
    {
      "姓名": "/",
      "装维账号": "18886720223",
      "网格": "威宁县",
      "日期": "3月",
      "呼入总量": 5,
      "一次接听量": 3,
      "一次接听率": 60.0,
      "回拨次数": 0,
      "真实接听率": 60.0,
      "真实未接通次数": 2
    },
    {
      "姓名": "/",
      "装维账号": "18886720268",
      "网格": "威宁县",
      "日期": "3月",
      "呼入总量": 4,
      "一次接听量": 0,
      "一次接听率": 0.0,
      "回拨次数": 2,
      "真实接听率": 50.0,
      "真实未接通次数": 2
    },
    {
      "姓名": "/",
      "装维账号": "19816605671",
      "网格": "威宁县",
      "日期": "3月",
      "呼入总量": 11,
      "一次接听量": 2,
      "一次接听率": 18.18,
      "回拨次数": 0,
      "真实接听率": 18.18,
      "真实未接通次数": 9
    },
    {
      "姓名": "/",
      "装维账号": "19816625431",
      "网格": "威宁县",
      "日期": "3月",
      "呼入总量": 3,
      "一次接听量": 1,
      "一次接听率": 33.33,
      "回拨次数": 0,
      "真实接听率": 33.33,
      "真实未接通次数": 2
    },
    {
      "姓名": "/",
      "装维账号": "19886927604",
      "网格": "威宁县",
      "日期": "3月",
      "呼入总量": 96,
      "一次接听量": 2,
      "一次接听率": 2.08,
      "回拨次数": 3,
      "真实接听率": 5.21,
      "真实未接通次数": 91
    }
  ],
  "毕节-黔西县": [
    {
      "姓名": "/",
      "装维账号": "18885704190",
      "网格": "黔西县",
      "日期": "3月",
      "呼入总量": 63,
      "一次接听量": 1,
      "一次接听率": 1.59,
      "回拨次数": 0,
      "真实接听率": 1.59,
      "真实未接通次数": 62
    },
    {
      "姓名": "/",
      "装维账号": "18885704529",
      "网格": "黔西县",
      "日期": "3月",
      "呼入总量": 48,
      "一次接听量": 14,
      "一次接听率": 29.17,
      "回拨次数": 3,
      "真实接听率": 35.42,
      "真实未接通次数": 31
    },
    {
      "姓名": "/",
      "装维账号": "18885732917",
      "网格": "黔西县",
      "日期": "3月",
      "呼入总量": 3,
      "一次接听量": 0,
      "一次接听率": 0.0,
      "回拨次数": 2,
      "真实接听率": 66.67,
      "真实未接通次数": 1
    },
    {
      "姓名": "/",
      "装维账号": "18886720501",
      "网格": "黔西县",
      "日期": "3月",
      "呼入总量": 2,
      "一次接听量": 1,
      "一次接听率": 50.0,
      "回拨次数": 0,
      "真实接听率": 50.0,
      "真实未接通次数": 1
    },
    {
      "姓名": "/",
      "装维账号": "18886720502",
      "网格": "黔西县",
      "日期": "3月",
      "呼入总量": 47,
      "一次接听量": 21,
      "一次接听率": 44.68,
      "回拨次数": 5,
      "真实接听率": 55.32,
      "真实未接通次数": 21
    },
    {
      "姓名": "/",
      "装维账号": "18886720508",
      "网格": "黔西县",
      "日期": "3月",
      "呼入总量": 12,
      "一次接听量": 3,
      "一次接听率": 25.0,
      "回拨次数": 3,
      "真实接听率": 50.0,
      "真实未接通次数": 6
    },
    {
      "姓名": "/",
      "装维账号": "18886720510",
      "网格": "黔西县",
      "日期": "3月",
      "呼入总量": 12,
      "一次接听量": 2,
      "一次接听率": 16.67,
      "回拨次数": 0,
      "真实接听率": 16.67,
      "真实未接通次数": 10
    },
    {
      "姓名": "/",
      "装维账号": "18886720519",
      "网格": "黔西县",
      "日期": "3月",
      "呼入总量": 8,
      "一次接听量": 0,
      "一次接听率": 0.0,
      "回拨次数": 3,
      "真实接听率": 37.5,
      "真实未接通次数": 5
    },
    {
      "姓名": "/",
      "装维账号": "18886720523",
      "网格": "黔西县",
      "日期": "3月",
      "呼入总量": 2,
      "一次接听量": 1,
      "一次接听率": 50.0,
      "回拨次数": 0,
      "真实接听率": 50.0,
      "真实未接通次数": 1
    },
    {
      "姓名": "/",
      "装维账号": "18886720527",
      "网格": "黔西县",
      "日期": "3月",
      "呼入总量": 67,
      "一次接听量": 32,
      "一次接听率": 47.76,
      "回拨次数": 7,
      "真实接听率": 58.21,
      "真实未接通次数": 28
    },
    {
      "姓名": "/",
      "装维账号": "18886720528",
      "网格": "黔西县",
      "日期": "3月",
      "呼入总量": 2,
      "一次接听量": 1,
      "一次接听率": 50.0,
      "回拨次数": 0,
      "真实接听率": 50.0,
      "真实未接通次数": 1
    },
    {
      "姓名": "/",
      "装维账号": "18886720556",
      "网格": "黔西县",
      "日期": "3月",
      "呼入总量": 48,
      "一次接听量": 4,
      "一次接听率": 8.33,
      "回拨次数": 0,
      "真实接听率": 8.33,
      "真实未接通次数": 44
    },
    {
      "姓名": "/",
      "装维账号": "18886720558",
      "网格": "黔西县",
      "日期": "3月",
      "呼入总量": 3,
      "一次接听量": 2,
      "一次接听率": 66.67,
      "回拨次数": 0,
      "真实接听率": 66.67,
      "真实未接通次数": 1
    },
    {
      "姓名": "/",
      "装维账号": "18886720562",
      "网格": "黔西县",
      "日期": "3月",
      "呼入总量": 120,
      "一次接听量": 30,
      "一次接听率": 25.0,
      "回拨次数": 20,
      "真实接听率": 41.67,
      "真实未接通次数": 70
    },
    {
      "姓名": "/",
      "装维账号": "18886720565",
      "网格": "黔西县",
      "日期": "3月",
      "呼入总量": 3,
      "一次接听量": 1,
      "一次接听率": 33.33,
      "回拨次数": 0,
      "真实接听率": 33.33,
      "真实未接通次数": 2
    },
    {
      "姓名": "/",
      "装维账号": "18886720579",
      "网格": "黔西县",
      "日期": "3月",
      "呼入总量": 6,
      "一次接听量": 3,
      "一次接听率": 50.0,
      "回拨次数": 1,
      "真实接听率": 66.67,
      "真实未接通次数": 2
    },
    {
      "姓名": "/",
      "装维账号": "18886720587",
      "网格": "黔西县",
      "日期": "3月",
      "呼入总量": 43,
      "一次接听量": 4,
      "一次接听率": 9.3,
      "回拨次数": 3,
      "真实接听率": 16.28,
      "真实未接通次数": 36
    }
  ],
  "毕节-七星关区": [
    {
      "姓名": "/",
      "装维账号": "18886720027",
      "网格": "七星关区",
      "日期": "3月",
      "呼入总量": 20,
      "一次接听量": 1,
      "一次接听率": 5.0,
      "回拨次数": 3,
      "真实接听率": 20.0,
      "真实未接通次数": 16
    },
    {
      "姓名": "/",
      "装维账号": "18886720052",
      "网格": "七星关区",
      "日期": "3月",
      "呼入总量": 15,
      "一次接听量": 5,
      "一次接听率": 33.33,
      "回拨次数": 4,
      "真实接听率": 60.0,
      "真实未接通次数": 6
    },
    {
      "姓名": "/",
      "装维账号": "18886720059",
      "网格": "七星关区",
      "日期": "3月",
      "呼入总量": 8,
      "一次接听量": 0,
      "一次接听率": 0.0,
      "回拨次数": 5,
      "真实接听率": 62.5,
      "真实未接通次数": 3
    },
    {
      "姓名": "/",
      "装维账号": "18886720080",
      "网格": "七星关区",
      "日期": "3月",
      "呼入总量": 40,
      "一次接听量": 1,
      "一次接听率": 2.5,
      "回拨次数": 0,
      "真实接听率": 2.5,
      "真实未接通次数": 39
    },
    {
      "姓名": "/",
      "装维账号": "18886720119",
      "网格": "七星关区",
      "日期": "3月",
      "呼入总量": 11,
      "一次接听量": 7,
      "一次接听率": 63.64,
      "回拨次数": 0,
      "真实接听率": 63.64,
      "真实未接通次数": 4
    },
    {
      "姓名": "/",
      "装维账号": "18886720979",
      "网格": "七星关区",
      "日期": "3月",
      "呼入总量": 19,
      "一次接听量": 7,
      "一次接听率": 36.84,
      "回拨次数": 4,
      "真实接听率": 57.89,
      "真实未接通次数": 8
    },
    {
      "姓名": "/",
      "装维账号": "18886720985",
      "网格": "七星关区",
      "日期": "3月",
      "呼入总量": 20,
      "一次接听量": 1,
      "一次接听率": 5.0,
      "回拨次数": 0,
      "真实接听率": 5.0,
      "真实未接通次数": 19
    },
    {
      "姓名": "/",
      "装维账号": "18886721004",
      "网格": "七星关区",
      "日期": "3月",
      "呼入总量": 20,
      "一次接听量": 11,
      "一次接听率": 55.0,
      "回拨次数": 0,
      "真实接听率": 55.0,
      "真实未接通次数": 9
    },
    {
      "姓名": "/",
      "装维账号": "18886721026",
      "网格": "七星关区",
      "日期": "3月",
      "呼入总量": 6,
      "一次接听量": 4,
      "一次接听率": 66.67,
      "回拨次数": 0,
      "真实接听率": 66.67,
      "真实未接通次数": 2
    }
  ],
  "毕节-赫章县": [
    {
      "姓名": "/",
      "装维账号": "18886720286",
      "网格": "赫章县",
      "日期": "3月",
      "呼入总量": 5,
      "一次接听量": 2,
      "一次接听率": 40.0,
      "回拨次数": 0,
      "真实接听率": 40.0,
      "真实未接通次数": 3
    },
    {
      "姓名": "/",
      "装维账号": "18886720293",
      "网格": "赫章县",
      "日期": "3月",
      "呼入总量": 15,
      "一次接听量": 2,
      "一次接听率": 13.33,
      "回拨次数": 2,
      "真实接听率": 26.67,
      "真实未接通次数": 11
    },
    {
      "姓名": "/",
      "装维账号": "18886720300",
      "网格": "赫章县",
      "日期": "3月",
      "呼入总量": 5,
      "一次接听量": 1,
      "一次接听率": 20.0,
      "回拨次数": 2,
      "真实接听率": 60.0,
      "真实未接通次数": 2
    },
    {
      "姓名": "/",
      "装维账号": "18886720301",
      "网格": "赫章县",
      "日期": "3月",
      "呼入总量": 16,
      "一次接听量": 1,
      "一次接听率": 6.25,
      "回拨次数": 4,
      "真实接听率": 31.25,
      "真实未接通次数": 11
    },
    {
      "姓名": "/",
      "装维账号": "18886720308",
      "网格": "赫章县",
      "日期": "3月",
      "呼入总量": 3,
      "一次接听量": 0,
      "一次接听率": 0.0,
      "回拨次数": 1,
      "真实接听率": 33.33,
      "真实未接通次数": 2
    },
    {
      "姓名": "/",
      "装维账号": "18886720318",
      "网格": "赫章县",
      "日期": "3月",
      "呼入总量": 12,
      "一次接听量": 1,
      "一次接听率": 8.33,
      "回拨次数": 4,
      "真实接听率": 41.67,
      "真实未接通次数": 7
    },
    {
      "姓名": "/",
      "装维账号": "18886720331",
      "网格": "赫章县",
      "日期": "3月",
      "呼入总量": 19,
      "一次接听量": 9,
      "一次接听率": 47.37,
      "回拨次数": 1,
      "真实接听率": 52.63,
      "真实未接通次数": 9
    },
    {
      "姓名": "/",
      "装维账号": "18886720349",
      "网格": "赫章县",
      "日期": "3月",
      "呼入总量": 6,
      "一次接听量": 3,
      "一次接听率": 50.0,
      "回拨次数": 0,
      "真实接听率": 50.0,
      "真实未接通次数": 3
    },
    {
      "姓名": "/",
      "装维账号": "18886720353",
      "网格": "赫章县",
      "日期": "3月",
      "呼入总量": 2,
      "一次接听量": 1,
      "一次接听率": 50.0,
      "回拨次数": 0,
      "真实接听率": 50.0,
      "真实未接通次数": 1
    },
    {
      "姓名": "/",
      "装维账号": "18886720356",
      "网格": "赫章县",
      "日期": "3月",
      "呼入总量": 23,
      "一次接听量": 8,
      "一次接听率": 34.78,
      "回拨次数": 8,
      "真实接听率": 69.57,
      "真实未接通次数": 7
    },
    {
      "姓名": "/",
      "装维账号": "18886720359",
      "网格": "赫章县",
      "日期": "3月",
      "呼入总量": 7,
      "一次接听量": 1,
      "一次接听率": 14.29,
      "回拨次数": 3,
      "真实接听率": 57.14,
      "真实未接通次数": 3
    },
    {
      "姓名": "/",
      "装维账号": "18886720363",
      "网格": "赫章县",
      "日期": "3月",
      "呼入总量": 9,
      "一次接听量": 4,
      "一次接听率": 44.44,
      "回拨次数": 0,
      "真实接听率": 44.44,
      "真实未接通次数": 5
    },
    {
      "姓名": "/",
      "装维账号": "18886720376",
      "网格": "赫章县",
      "日期": "3月",
      "呼入总量": 24,
      "一次接听量": 6,
      "一次接听率": 25.0,
      "回拨次数": 5,
      "真实接听率": 45.83,
      "真实未接通次数": 13
    },
    {
      "姓名": "/",
      "装维账号": "18886720378",
      "网格": "赫章县",
      "日期": "3月",
      "呼入总量": 3,
      "一次接听量": 2,
      "一次接听率": 66.67,
      "回拨次数": 0,
      "真实接听率": 66.67,
      "真实未接通次数": 1
    }
  ],
  "毕节-纳雍县": [
    {
      "姓名": "/",
      "装维账号": "18886720391",
      "网格": "纳雍县",
      "日期": "3月",
      "呼入总量": 3,
      "一次接听量": 1,
      "一次接听率": 33.33,
      "回拨次数": 0,
      "真实接听率": 33.33,
      "真实未接通次数": 2
    },
    {
      "姓名": "/",
      "装维账号": "18886720392",
      "网格": "纳雍县",
      "日期": "3月",
      "呼入总量": 23,
      "一次接听量": 7,
      "一次接听率": 30.43,
      "回拨次数": 8,
      "真实接听率": 65.22,
      "真实未接通次数": 8
    },
    {
      "姓名": "/",
      "装维账号": "18886720395",
      "网格": "纳雍县",
      "日期": "3月",
      "呼入总量": 6,
      "一次接听量": 4,
      "一次接听率": 66.67,
      "回拨次数": 0,
      "真实接听率": 66.67,
      "真实未接通次数": 2
    },
    {
      "姓名": "/",
      "装维账号": "18886720398",
      "网格": "纳雍县",
      "日期": "3月",
      "呼入总量": 3,
      "一次接听量": 2,
      "一次接听率": 66.67,
      "回拨次数": 0,
      "真实接听率": 66.67,
      "真实未接通次数": 1
    },
    {
      "姓名": "/",
      "装维账号": "18886720400",
      "网格": "纳雍县",
      "日期": "3月",
      "呼入总量": 6,
      "一次接听量": 1,
      "一次接听率": 16.67,
      "回拨次数": 3,
      "真实接听率": 66.67,
      "真实未接通次数": 2
    },
    {
      "姓名": "/",
      "装维账号": "18886720402",
      "网格": "纳雍县",
      "日期": "3月",
      "呼入总量": 11,
      "一次接听量": 7,
      "一次接听率": 63.64,
      "回拨次数": 0,
      "真实接听率": 63.64,
      "真实未接通次数": 4
    },
    {
      "姓名": "/",
      "装维账号": "18886720420",
      "网格": "纳雍县",
      "日期": "3月",
      "呼入总量": 19,
      "一次接听量": 3,
      "一次接听率": 15.79,
      "回拨次数": 0,
      "真实接听率": 15.79,
      "真实未接通次数": 16
    },
    {
      "姓名": "/",
      "装维账号": "18886720421",
      "网格": "纳雍县",
      "日期": "3月",
      "呼入总量": 4,
      "一次接听量": 1,
      "一次接听率": 25.0,
      "回拨次数": 0,
      "真实接听率": 25.0,
      "真实未接通次数": 3
    },
    {
      "姓名": "/",
      "装维账号": "18886720449",
      "网格": "纳雍县",
      "日期": "3月",
      "呼入总量": 35,
      "一次接听量": 13,
      "一次接听率": 37.14,
      "回拨次数": 2,
      "真实接听率": 42.86,
      "真实未接通次数": 20
    },
    {
      "姓名": "/",
      "装维账号": "18886720455",
      "网格": "纳雍县",
      "日期": "3月",
      "呼入总量": 6,
      "一次接听量": 4,
      "一次接听率": 66.67,
      "回拨次数": 0,
      "真实接听率": 66.67,
      "真实未接通次数": 2
    },
    {
      "姓名": "/",
      "装维账号": "18886720462",
      "网格": "纳雍县",
      "日期": "3月",
      "呼入总量": 9,
      "一次接听量": 0,
      "一次接听率": 0.0,
      "回拨次数": 2,
      "真实接听率": 22.22,
      "真实未接通次数": 7
    }
  ],
  "毕节-大方县": [
    {
      "姓名": "/",
      "装维账号": "18886720607",
      "网格": "大方县",
      "日期": "3月",
      "呼入总量": 82,
      "一次接听量": 15,
      "一次接听率": 18.29,
      "回拨次数": 6,
      "真实接听率": 25.61,
      "真实未接通次数": 61
    },
    {
      "姓名": "/",
      "装维账号": "18886720610",
      "网格": "大方县",
      "日期": "3月",
      "呼入总量": 3,
      "一次接听量": 1,
      "一次接听率": 33.33,
      "回拨次数": 0,
      "真实接听率": 33.33,
      "真实未接通次数": 2
    },
    {
      "姓名": "/",
      "装维账号": "18886720611",
      "网格": "大方县",
      "日期": "3月",
      "呼入总量": 9,
      "一次接听量": 1,
      "一次接听率": 11.11,
      "回拨次数": 5,
      "真实接听率": 66.67,
      "真实未接通次数": 3
    },
    {
      "姓名": "/",
      "装维账号": "18886720612",
      "网格": "大方县",
      "日期": "3月",
      "呼入总量": 3,
      "一次接听量": 2,
      "一次接听率": 66.67,
      "回拨次数": 0,
      "真实接听率": 66.67,
      "真实未接通次数": 1
    },
    {
      "姓名": "/",
      "装维账号": "18886720618",
      "网格": "大方县",
      "日期": "3月",
      "呼入总量": 64,
      "一次接听量": 25,
      "一次接听率": 39.06,
      "回拨次数": 7,
      "真实接听率": 50.0,
      "真实未接通次数": 32
    },
    {
      "姓名": "/",
      "装维账号": "18886720619",
      "网格": "大方县",
      "日期": "3月",
      "呼入总量": 61,
      "一次接听量": 9,
      "一次接听率": 14.75,
      "回拨次数": 17,
      "真实接听率": 42.62,
      "真实未接通次数": 35
    },
    {
      "姓名": "/",
      "装维账号": "18886720633",
      "网格": "大方县",
      "日期": "3月",
      "呼入总量": 21,
      "一次接听量": 7,
      "一次接听率": 33.33,
      "回拨次数": 7,
      "真实接听率": 66.67,
      "真实未接通次数": 7
    },
    {
      "姓名": "/",
      "装维账号": "18886720650",
      "网格": "大方县",
      "日期": "3月",
      "呼入总量": 2,
      "一次接听量": 1,
      "一次接听率": 50.0,
      "回拨次数": 0,
      "真实接听率": 50.0,
      "真实未接通次数": 1
    },
    {
      "姓名": "/",
      "装维账号": "18886720651",
      "网格": "大方县",
      "日期": "3月",
      "呼入总量": 10,
      "一次接听量": 2,
      "一次接听率": 20.0,
      "回拨次数": 2,
      "真实接听率": 40.0,
      "真实未接通次数": 6
    },
    {
      "姓名": "/",
      "装维账号": "18886720662",
      "网格": "大方县",
      "日期": "3月",
      "呼入总量": 24,
      "一次接听量": 1,
      "一次接听率": 4.17,
      "回拨次数": 0,
      "真实接听率": 4.17,
      "真实未接通次数": 23
    },
    {
      "姓名": "/",
      "装维账号": "18886720668",
      "网格": "大方县",
      "日期": "3月",
      "呼入总量": 35,
      "一次接听量": 9,
      "一次接听率": 25.71,
      "回拨次数": 0,
      "真实接听率": 25.71,
      "真实未接通次数": 26
    },
    {
      "姓名": "/",
      "装维账号": "18886720700",
      "网格": "大方县",
      "日期": "3月",
      "呼入总量": 6,
      "一次接听量": 3,
      "一次接听率": 50.0,
      "回拨次数": 0,
      "真实接听率": 50.0,
      "真实未接通次数": 3
    }
  ],
  "毕节-金沙县": [
    {
      "姓名": "/",
      "装维账号": "18886720706",
      "网格": "金沙县",
      "日期": "3月",
      "呼入总量": 5,
      "一次接听量": 1,
      "一次接听率": 20.0,
      "回拨次数": 2,
      "真实接听率": 60.0,
      "真实未接通次数": 2
    },
    {
      "姓名": "/",
      "装维账号": "18886720708",
      "网格": "金沙县",
      "日期": "3月",
      "呼入总量": 13,
      "一次接听量": 3,
      "一次接听率": 23.08,
      "回拨次数": 6,
      "真实接听率": 69.23,
      "真实未接通次数": 4
    },
    {
      "姓名": "/",
      "装维账号": "18886720711",
      "网格": "金沙县",
      "日期": "3月",
      "呼入总量": 18,
      "一次接听量": 6,
      "一次接听率": 33.33,
      "回拨次数": 4,
      "真实接听率": 55.56,
      "真实未接通次数": 8
    },
    {
      "姓名": "/",
      "装维账号": "18886720717",
      "网格": "金沙县",
      "日期": "3月",
      "呼入总量": 2,
      "一次接听量": 1,
      "一次接听率": 50.0,
      "回拨次数": 0,
      "真实接听率": 50.0,
      "真实未接通次数": 1
    },
    {
      "姓名": "/",
      "装维账号": "18886720725",
      "网格": "金沙县",
      "日期": "3月",
      "呼入总量": 34,
      "一次接听量": 17,
      "一次接听率": 50.0,
      "回拨次数": 2,
      "真实接听率": 55.88,
      "真实未接通次数": 15
    },
    {
      "姓名": "/",
      "装维账号": "18886720728",
      "网格": "金沙县",
      "日期": "3月",
      "呼入总量": 6,
      "一次接听量": 0,
      "一次接听率": 0.0,
      "回拨次数": 2,
      "真实接听率": 33.33,
      "真实未接通次数": 4
    },
    {
      "姓名": "/",
      "装维账号": "18886720734",
      "网格": "金沙县",
      "日期": "3月",
      "呼入总量": 25,
      "一次接听量": 7,
      "一次接听率": 28.0,
      "回拨次数": 6,
      "真实接听率": 52.0,
      "真实未接通次数": 12
    },
    {
      "姓名": "/",
      "装维账号": "18886720736",
      "网格": "金沙县",
      "日期": "3月",
      "呼入总量": 16,
      "一次接听量": 11,
      "一次接听率": 68.75,
      "回拨次数": 0,
      "真实接听率": 68.75,
      "真实未接通次数": 5
    },
    {
      "姓名": "/",
      "装维账号": "18886720763",
      "网格": "金沙县",
      "日期": "3月",
      "呼入总量": 20,
      "一次接听量": 13,
      "一次接听率": 65.0,
      "回拨次数": 0,
      "真实接听率": 65.0,
      "真实未接通次数": 7
    },
    {
      "姓名": "/",
      "装维账号": "18886720768",
      "网格": "金沙县",
      "日期": "3月",
      "呼入总量": 8,
      "一次接听量": 2,
      "一次接听率": 25.0,
      "回拨次数": 3,
      "真实接听率": 62.5,
      "真实未接通次数": 3
    },
    {
      "姓名": "/",
      "装维账号": "18886720769",
      "网格": "金沙县",
      "日期": "3月",
      "呼入总量": 45,
      "一次接听量": 5,
      "一次接听率": 11.11,
      "回拨次数": 0,
      "真实接听率": 11.11,
      "真实未接通次数": 40
    },
    {
      "姓名": "/",
      "装维账号": "18886720773",
      "网格": "金沙县",
      "日期": "3月",
      "呼入总量": 18,
      "一次接听量": 6,
      "一次接听率": 33.33,
      "回拨次数": 0,
      "真实接听率": 33.33,
      "真实未接通次数": 12
    },
    {
      "姓名": "/",
      "装维账号": "18886720803",
      "网格": "金沙县",
      "日期": "3月",
      "呼入总量": 3,
      "一次接听量": 2,
      "一次接听率": 66.67,
      "回拨次数": 0,
      "真实接听率": 66.67,
      "真实未接通次数": 1
    },
    {
      "姓名": "/",
      "装维账号": "18886721023",
      "网格": "金沙县",
      "日期": "3月",
      "呼入总量": 9,
      "一次接听量": 3,
      "一次接听率": 33.33,
      "回拨次数": 0,
      "真实接听率": 33.33,
      "真实未接通次数": 6
    },
    {
      "姓名": "/",
      "装维账号": "18886721080",
      "网格": "金沙县",
      "日期": "3月",
      "呼入总量": 2,
      "一次接听量": 1,
      "一次接听率": 50.0,
      "回拨次数": 0,
      "真实接听率": 50.0,
      "真实未接通次数": 1
    }
  ],
  "毕节-织金县": [
    {
      "姓名": "/",
      "装维账号": "18886720815",
      "网格": "织金县",
      "日期": "3月",
      "呼入总量": 9,
      "一次接听量": 4,
      "一次接听率": 44.44,
      "回拨次数": 0,
      "真实接听率": 44.44,
      "真实未接通次数": 5
    },
    {
      "姓名": "/",
      "装维账号": "18886720818",
      "网格": "织金县",
      "日期": "3月",
      "呼入总量": 36,
      "一次接听量": 16,
      "一次接听率": 44.44,
      "回拨次数": 5,
      "真实接听率": 58.33,
      "真实未接通次数": 15
    },
    {
      "姓名": "/",
      "装维账号": "18886720826",
      "网格": "织金县",
      "日期": "3月",
      "呼入总量": 41,
      "一次接听量": 12,
      "一次接听率": 29.27,
      "回拨次数": 16,
      "真实接听率": 68.29,
      "真实未接通次数": 13
    },
    {
      "姓名": "/",
      "装维账号": "18886720830",
      "网格": "织金县",
      "日期": "3月",
      "呼入总量": 18,
      "一次接听量": 6,
      "一次接听率": 33.33,
      "回拨次数": 0,
      "真实接听率": 33.33,
      "真实未接通次数": 12
    },
    {
      "姓名": "/",
      "装维账号": "18886720849",
      "网格": "织金县",
      "日期": "3月",
      "呼入总量": 17,
      "一次接听量": 11,
      "一次接听率": 64.71,
      "回拨次数": 0,
      "真实接听率": 64.71,
      "真实未接通次数": 6
    },
    {
      "姓名": "/",
      "装维账号": "18886720858",
      "网格": "织金县",
      "日期": "3月",
      "呼入总量": 33,
      "一次接听量": 10,
      "一次接听率": 30.3,
      "回拨次数": 4,
      "真实接听率": 42.42,
      "真实未接通次数": 19
    },
    {
      "姓名": "/",
      "装维账号": "18886720860",
      "网格": "织金县",
      "日期": "3月",
      "呼入总量": 28,
      "一次接听量": 5,
      "一次接听率": 17.86,
      "回拨次数": 3,
      "真实接听率": 28.57,
      "真实未接通次数": 20
    },
    {
      "姓名": "/",
      "装维账号": "18886720862",
      "网格": "织金县",
      "日期": "3月",
      "呼入总量": 3,
      "一次接听量": 0,
      "一次接听率": 0.0,
      "回拨次数": 2,
      "真实接听率": 66.67,
      "真实未接通次数": 1
    },
    {
      "姓名": "/",
      "装维账号": "18886720868",
      "网格": "织金县",
      "日期": "3月",
      "呼入总量": 8,
      "一次接听量": 5,
      "一次接听率": 62.5,
      "回拨次数": 0,
      "真实接听率": 62.5,
      "真实未接通次数": 3
    },
    {
      "姓名": "/",
      "装维账号": "18886720881",
      "网格": "织金县",
      "日期": "3月",
      "呼入总量": 17,
      "一次接听量": 4,
      "一次接听率": 23.53,
      "回拨次数": 6,
      "真实接听率": 58.82,
      "真实未接通次数": 7
    },
    {
      "姓名": "/",
      "装维账号": "18886720886",
      "网格": "织金县",
      "日期": "3月",
      "呼入总量": 5,
      "一次接听量": 2,
      "一次接听率": 40.0,
      "回拨次数": 0,
      "真实接听率": 40.0,
      "真实未接通次数": 3
    },
    {
      "姓名": "/",
      "装维账号": "18886720897",
      "网格": "织金县",
      "日期": "3月",
      "呼入总量": 2,
      "一次接听量": 1,
      "一次接听率": 50.0,
      "回拨次数": 0,
      "真实接听率": 50.0,
      "真实未接通次数": 1
    },
    {
      "姓名": "/",
      "装维账号": "18886720911",
      "网格": "织金县",
      "日期": "3月",
      "呼入总量": 11,
      "一次接听量": 2,
      "一次接听率": 18.18,
      "回拨次数": 4,
      "真实接听率": 54.55,
      "真实未接通次数": 5
    }
  ],
  "毕节-金海湖区": [
    {
      "姓名": "/",
      "装维账号": "18886720917",
      "网格": "金海湖区",
      "日期": "3月",
      "呼入总量": 33,
      "一次接听量": 12,
      "一次接听率": 36.36,
      "回拨次数": 6,
      "真实接听率": 54.55,
      "真实未接通次数": 15
    },
    {
      "姓名": "/",
      "装维账号": "18886720925",
      "网格": "金海湖区",
      "日期": "3月",
      "呼入总量": 22,
      "一次接听量": 5,
      "一次接听率": 22.73,
      "回拨次数": 6,
      "真实接听率": 50.0,
      "真实未接通次数": 11
    },
    {
      "姓名": "/",
      "装维账号": "18886720929",
      "网格": "金海湖区",
      "日期": "3月",
      "呼入总量": 48,
      "一次接听量": 1,
      "一次接听率": 2.08,
      "回拨次数": 0,
      "真实接听率": 2.08,
      "真实未接通次数": 47
    },
    {
      "姓名": "/",
      "装维账号": "18886720933",
      "网格": "金海湖区",
      "日期": "3月",
      "呼入总量": 26,
      "一次接听量": 9,
      "一次接听率": 34.62,
      "回拨次数": 5,
      "真实接听率": 53.85,
      "真实未接通次数": 12
    },
    {
      "姓名": "/",
      "装维账号": "18886720936",
      "网格": "金海湖区",
      "日期": "3月",
      "呼入总量": 20,
      "一次接听量": 3,
      "一次接听率": 15.0,
      "回拨次数": 10,
      "真实接听率": 65.0,
      "真实未接通次数": 7
    },
    {
      "姓名": "/",
      "装维账号": "18886720937",
      "网格": "金海湖区",
      "日期": "3月",
      "呼入总量": 37,
      "一次接听量": 6,
      "一次接听率": 16.22,
      "回拨次数": 2,
      "真实接听率": 21.62,
      "真实未接通次数": 29
    },
    {
      "姓名": "/",
      "装维账号": "18886720939",
      "网格": "金海湖区",
      "日期": "3月",
      "呼入总量": 4,
      "一次接听量": 1,
      "一次接听率": 25.0,
      "回拨次数": 0,
      "真实接听率": 25.0,
      "真实未接通次数": 3
    }
  ],
  "黔西南-兴义市": [
    {
      "姓名": "/",
      "装维账号": "15117390066",
      "网格": "兴义市",
      "日期": "3月",
      "呼入总量": 91,
      "一次接听量": 38,
      "一次接听率": 41.76,
      "回拨次数": 24,
      "真实接听率": 68.13,
      "真实未接通次数": 29
    },
    {
      "姓名": "sf_段国珊",
      "装维账号": "18208639980",
      "网格": "兴义市城区代维驻点集客家客维护组1",
      "日期": "3月",
      "呼入总量": 96,
      "一次接听量": 1,
      "一次接听率": 1.04,
      "回拨次数": 5,
      "真实接听率": 6.25,
      "真实未接通次数": 90
    },
    {
      "姓名": "王化龙",
      "装维账号": "18286956887",
      "网格": "兴义市城区代维驻点集客家客维护组3",
      "日期": "3月",
      "呼入总量": 99,
      "一次接听量": 14,
      "一次接听率": 14.14,
      "回拨次数": 29,
      "真实接听率": 43.43,
      "真实未接通次数": 56
    },
    {
      "姓名": "郑祥",
      "装维账号": "18296049816",
      "网格": "兴义市城区代维驻点集客家客维护组1",
      "日期": "3月",
      "呼入总量": 75,
      "一次接听量": 26,
      "一次接听率": 34.67,
      "回拨次数": 26,
      "真实接听率": 69.33,
      "真实未接通次数": 23
    },
    {
      "姓名": "sf_陈俊",
      "装维账号": "18785918353",
      "网格": "兴义市城区代维驻点集客家客维护组3",
      "日期": "3月",
      "呼入总量": 16,
      "一次接听量": 8,
      "一次接听率": 50.0,
      "回拨次数": 0,
      "真实接听率": 50.0,
      "真实未接通次数": 8
    },
    {
      "姓名": "吴海洋",
      "装维账号": "18788743552",
      "网格": "兴义市城区代维驻点集客家客维护组1",
      "日期": "3月",
      "呼入总量": 104,
      "一次接听量": 31,
      "一次接听率": 29.81,
      "回拨次数": 40,
      "真实接听率": 68.27,
      "真实未接通次数": 33
    },
    {
      "姓名": "撒俊旭",
      "装维账号": "18885936881",
      "网格": "兴义市城区代维驻点集客家客维护组2",
      "日期": "3月",
      "呼入总量": 140,
      "一次接听量": 47,
      "一次接听率": 33.57,
      "回拨次数": 23,
      "真实接听率": 50.0,
      "真实未接通次数": 70
    }
  ],
  "黔西南-晴隆县": [
    {
      "姓名": "sf_商爽",
      "装维账号": "15186441072",
      "网格": "晴隆县集客家客代维维护小组2",
      "日期": "3月",
      "呼入总量": 59,
      "一次接听量": 23,
      "一次接听率": 38.98,
      "回拨次数": 14,
      "真实接听率": 62.71,
      "真实未接通次数": 22
    }
  ],
  "黔西南-兴仁市": [
    {
      "姓名": "sf_肖大灿",
      "装维账号": "18208611919",
      "网格": "兴仁县城区代维驻点集客家客维护组1",
      "日期": "3月",
      "呼入总量": 328,
      "一次接听量": 95,
      "一次接听率": 28.96,
      "回拨次数": 114,
      "真实接听率": 63.72,
      "真实未接通次数": 119
    }
  ],
  "黔西南-册亨县": [
    {
      "姓名": "黄德斌",
      "装维账号": "18208614994",
      "网格": "册亨县城区代维驻点集客家客维护组1",
      "日期": "3月",
      "呼入总量": 50,
      "一次接听量": 2,
      "一次接听率": 4.0,
      "回拨次数": 12,
      "真实接听率": 28.0,
      "真实未接通次数": 36
    }
  ],
  "黔西南-贞丰县": [
    {
      "姓名": "sf_王耀",
      "装维账号": "18208627228",
      "网格": "贞丰县城区代维驻点集客家客维护组2",
      "日期": "3月",
      "呼入总量": 162,
      "一次接听量": 51,
      "一次接听率": 31.48,
      "回拨次数": 55,
      "真实接听率": 65.43,
      "真实未接通次数": 56
    },
    {
      "姓名": "/",
      "装维账号": "18386418088",
      "网格": "贞丰县",
      "日期": "3月",
      "呼入总量": 88,
      "一次接听量": 11,
      "一次接听率": 12.5,
      "回拨次数": 0,
      "真实接听率": 12.5,
      "真实未接通次数": 77
    },
    {
      "姓名": "帅显启",
      "装维账号": "18788799089",
      "网格": "贞丰县城区代维驻点集客家客维护组2",
      "日期": "3月",
      "呼入总量": 48,
      "一次接听量": 14,
      "一次接听率": 29.17,
      "回拨次数": 15,
      "真实接听率": 60.42,
      "真实未接通次数": 19
    }
  ],
  "黔西南-望谟县": [
    {
      "姓名": "黎涛",
      "装维账号": "18208687673",
      "网格": "望谟县城区代维驻点集客家客维护组1",
      "日期": "3月",
      "呼入总量": 36,
      "一次接听量": 9,
      "一次接听率": 25.0,
      "回拨次数": 0,
      "真实接听率": 25.0,
      "真实未接通次数": 27
    },
    {
      "姓名": "sf_黄调",
      "装维账号": "19885465645",
      "网格": "望谟县城区代维驻点集客家客维护组1",
      "日期": "3月",
      "呼入总量": 82,
      "一次接听量": 1,
      "一次接听率": 1.22,
      "回拨次数": 0,
      "真实接听率": 1.22,
      "真实未接通次数": 81
    },
    {
      "姓名": "何永坤",
      "装维账号": "19885469046",
      "网格": "望谟县城区代维驻点集客家客维护组1",
      "日期": "3月",
      "呼入总量": 108,
      "一次接听量": 30,
      "一次接听率": 27.78,
      "回拨次数": 26,
      "真实接听率": 51.85,
      "真实未接通次数": 52
    }
  ],
  "黔西南-普安县": [
    {
      "姓名": "周伟",
      "装维账号": "18744969290",
      "网格": "普安县城区代维驻点集客家客维护组1",
      "日期": "3月",
      "呼入总量": 52,
      "一次接听量": 7,
      "一次接听率": 13.46,
      "回拨次数": 5,
      "真实接听率": 23.08,
      "真实未接通次数": 40
    }
  ],
  "黔西南-安龙县": [
    {
      "姓名": "华德勇",
      "装维账号": "18748911996",
      "网格": "安龙县城区代维驻点集客家客维护组2",
      "日期": "3月",
      "呼入总量": 78,
      "一次接听量": 35,
      "一次接听率": 44.87,
      "回拨次数": 19,
      "真实接听率": 69.23,
      "真实未接通次数": 24
    }
  ],
  "遵义-务川县": [
    {
      "姓名": "/",
      "装维账号": "19585233520",
      "网格": "务川县",
      "日期": "3月",
      "呼入总量": 13,
      "一次接听量": 7,
      "一次接听率": 53.85,
      "回拨次数": 2,
      "真实接听率": 69.23,
      "真实未接通次数": 4
    }
  ],
  "遵义-余庆县": [
    {
      "姓名": "/",
      "装维账号": "19585270048",
      "网格": "余庆县",
      "日期": "3月",
      "呼入总量": 3,
      "一次接听量": 2,
      "一次接听率": 66.67,
      "回拨次数": 0,
      "真实接听率": 66.67,
      "真实未接通次数": 1
    }
  ],
  "遵义-红花岗区": [
    {
      "姓名": "/",
      "装维账号": "19585270109",
      "网格": "红花岗区",
      "日期": "3月",
      "呼入总量": 7,
      "一次接听量": 3,
      "一次接听率": 42.86,
      "回拨次数": 0,
      "真实接听率": 42.86,
      "真实未接通次数": 4
    },
    {
      "姓名": "/",
      "装维账号": "19585270300",
      "网格": "红花岗区",
      "日期": "3月",
      "呼入总量": 22,
      "一次接听量": 4,
      "一次接听率": 18.18,
      "回拨次数": 0,
      "真实接听率": 18.18,
      "真实未接通次数": 18
    },
    {
      "姓名": "/",
      "装维账号": "19585271231",
      "网格": "红花岗区",
      "日期": "3月",
      "呼入总量": 23,
      "一次接听量": 12,
      "一次接听率": 52.17,
      "回拨次数": 2,
      "真实接听率": 60.87,
      "真实未接通次数": 9
    },
    {
      "姓名": "/",
      "装维账号": "19585271336",
      "网格": "红花岗区",
      "日期": "3月",
      "呼入总量": 8,
      "一次接听量": 5,
      "一次接听率": 62.5,
      "回拨次数": 0,
      "真实接听率": 62.5,
      "真实未接通次数": 3
    },
    {
      "姓名": "/",
      "装维账号": "19585271517",
      "网格": "红花岗区",
      "日期": "3月",
      "呼入总量": 13,
      "一次接听量": 8,
      "一次接听率": 61.54,
      "回拨次数": 0,
      "真实接听率": 61.54,
      "真实未接通次数": 5
    },
    {
      "姓名": "/",
      "装维账号": "19585271669",
      "网格": "红花岗区",
      "日期": "3月",
      "呼入总量": 17,
      "一次接听量": 4,
      "一次接听率": 23.53,
      "回拨次数": 0,
      "真实接听率": 23.53,
      "真实未接通次数": 13
    }
  ],
  "遵义-播州区": [
    {
      "姓名": "/",
      "装维账号": "19585270169",
      "网格": "播州区",
      "日期": "3月",
      "呼入总量": 27,
      "一次接听量": 14,
      "一次接听率": 51.85,
      "回拨次数": 4,
      "真实接听率": 66.67,
      "真实未接通次数": 9
    },
    {
      "姓名": "/",
      "装维账号": "19585270192",
      "网格": "播州区",
      "日期": "3月",
      "呼入总量": 9,
      "一次接听量": 6,
      "一次接听率": 66.67,
      "回拨次数": 0,
      "真实接听率": 66.67,
      "真实未接通次数": 3
    },
    {
      "姓名": "/",
      "装维账号": "19585270230",
      "网格": "播州区",
      "日期": "3月",
      "呼入总量": 20,
      "一次接听量": 11,
      "一次接听率": 55.0,
      "回拨次数": 0,
      "真实接听率": 55.0,
      "真实未接通次数": 9
    },
    {
      "姓名": "/",
      "装维账号": "19585270239",
      "网格": "播州区",
      "日期": "3月",
      "呼入总量": 22,
      "一次接听量": 0,
      "一次接听率": 0.0,
      "回拨次数": 7,
      "真实接听率": 31.82,
      "真实未接通次数": 15
    },
    {
      "姓名": "/",
      "装维账号": "19585270264",
      "网格": "播州区",
      "日期": "3月",
      "呼入总量": 14,
      "一次接听量": 4,
      "一次接听率": 28.57,
      "回拨次数": 2,
      "真实接听率": 42.86,
      "真实未接通次数": 8
    },
    {
      "姓名": "/",
      "装维账号": "19585270275",
      "网格": "播州区",
      "日期": "3月",
      "呼入总量": 20,
      "一次接听量": 1,
      "一次接听率": 5.0,
      "回拨次数": 3,
      "真实接听率": 20.0,
      "真实未接通次数": 16
    },
    {
      "姓名": "/",
      "装维账号": "19585270279",
      "网格": "播州区",
      "日期": "3月",
      "呼入总量": 3,
      "一次接听量": 0,
      "一次接听率": 0.0,
      "回拨次数": 2,
      "真实接听率": 66.67,
      "真实未接通次数": 1
    },
    {
      "姓名": "/",
      "装维账号": "19585270282",
      "网格": "播州区",
      "日期": "3月",
      "呼入总量": 18,
      "一次接听量": 10,
      "一次接听率": 55.56,
      "回拨次数": 0,
      "真实接听率": 55.56,
      "真实未接通次数": 8
    },
    {
      "姓名": "/",
      "装维账号": "19585271055",
      "网格": "播州区",
      "日期": "3月",
      "呼入总量": 9,
      "一次接听量": 4,
      "一次接听率": 44.44,
      "回拨次数": 2,
      "真实接听率": 66.67,
      "真实未接通次数": 3
    },
    {
      "姓名": "/",
      "装维账号": "19585271169",
      "网格": "播州区",
      "日期": "3月",
      "呼入总量": 10,
      "一次接听量": 2,
      "一次接听率": 20.0,
      "回拨次数": 0,
      "真实接听率": 20.0,
      "真实未接通次数": 8
    },
    {
      "姓名": "/",
      "装维账号": "19585271308",
      "网格": "播州区",
      "日期": "3月",
      "呼入总量": 18,
      "一次接听量": 2,
      "一次接听率": 11.11,
      "回拨次数": 7,
      "真实接听率": 50.0,
      "真实未接通次数": 9
    }
  ],
  "遵义-凤冈县": [
    {
      "姓名": "/",
      "装维账号": "19585270455",
      "网格": "凤冈县",
      "日期": "3月",
      "呼入总量": 7,
      "一次接听量": 4,
      "一次接听率": 57.14,
      "回拨次数": 0,
      "真实接听率": 57.14,
      "真实未接通次数": 3
    },
    {
      "姓名": "/",
      "装维账号": "19585270533",
      "网格": "凤冈县",
      "日期": "3月",
      "呼入总量": 33,
      "一次接听量": 14,
      "一次接听率": 42.42,
      "回拨次数": 7,
      "真实接听率": 63.64,
      "真实未接通次数": 12
    },
    {
      "姓名": "/",
      "装维账号": "19585270586",
      "网格": "凤冈县",
      "日期": "3月",
      "呼入总量": 4,
      "一次接听量": 1,
      "一次接听率": 25.0,
      "回拨次数": 0,
      "真实接听率": 25.0,
      "真实未接通次数": 3
    },
    {
      "姓名": "/",
      "装维账号": "19585270710",
      "网格": "凤冈县",
      "日期": "3月",
      "呼入总量": 8,
      "一次接听量": 2,
      "一次接听率": 25.0,
      "回拨次数": 1,
      "真实接听率": 37.5,
      "真实未接通次数": 5
    },
    {
      "姓名": "/",
      "装维账号": "19585270757",
      "网格": "凤冈县",
      "日期": "3月",
      "呼入总量": 49,
      "一次接听量": 15,
      "一次接听率": 30.61,
      "回拨次数": 16,
      "真实接听率": 63.27,
      "真实未接通次数": 18
    }
  ],
  "遵义-正安县": [
    {
      "姓名": "/",
      "装维账号": "19585270590",
      "网格": "正安县",
      "日期": "3月",
      "呼入总量": 3,
      "一次接听量": 2,
      "一次接听率": 66.67,
      "回拨次数": 0,
      "真实接听率": 66.67,
      "真实未接通次数": 1
    }
  ],
  "遵义-湄潭县": [
    {
      "姓名": "/",
      "装维账号": "19585270604",
      "网格": "湄潭县",
      "日期": "3月",
      "呼入总量": 20,
      "一次接听量": 10,
      "一次接听率": 50.0,
      "回拨次数": 0,
      "真实接听率": 50.0,
      "真实未接通次数": 10
    },
    {
      "姓名": "/",
      "装维账号": "19585270623",
      "网格": "湄潭县",
      "日期": "3月",
      "呼入总量": 4,
      "一次接听量": 2,
      "一次接听率": 50.0,
      "回拨次数": 0,
      "真实接听率": 50.0,
      "真实未接通次数": 2
    },
    {
      "姓名": "/",
      "装维账号": "19585271210",
      "网格": "湄潭县",
      "日期": "3月",
      "呼入总量": 27,
      "一次接听量": 5,
      "一次接听率": 18.52,
      "回拨次数": 9,
      "真实接听率": 51.85,
      "真实未接通次数": 13
    }
  ],
  "遵义-道真县": [
    {
      "姓名": "/",
      "装维账号": "19585270667",
      "网格": "道真县",
      "日期": "3月",
      "呼入总量": 20,
      "一次接听量": 7,
      "一次接听率": 35.0,
      "回拨次数": 0,
      "真实接听率": 35.0,
      "真实未接通次数": 13
    },
    {
      "姓名": "/",
      "装维账号": "19585270860",
      "网格": "道真县",
      "日期": "3月",
      "呼入总量": 20,
      "一次接听量": 5,
      "一次接听率": 25.0,
      "回拨次数": 2,
      "真实接听率": 35.0,
      "真实未接通次数": 13
    },
    {
      "姓名": "/",
      "装维账号": "19585270944",
      "网格": "道真县",
      "日期": "3月",
      "呼入总量": 3,
      "一次接听量": 2,
      "一次接听率": 66.67,
      "回拨次数": 0,
      "真实接听率": 66.67,
      "真实未接通次数": 1
    },
    {
      "姓名": "/",
      "装维账号": "19585271235",
      "网格": "道真县",
      "日期": "3月",
      "呼入总量": 12,
      "一次接听量": 1,
      "一次接听率": 8.33,
      "回拨次数": 0,
      "真实接听率": 8.33,
      "真实未接通次数": 11
    },
    {
      "姓名": "/",
      "装维账号": "19585271318",
      "网格": "道真县",
      "日期": "3月",
      "呼入总量": 12,
      "一次接听量": 1,
      "一次接听率": 8.33,
      "回拨次数": 0,
      "真实接听率": 8.33,
      "真实未接通次数": 11
    }
  ],
  "遵义-绥阳县": [
    {
      "姓名": "/",
      "装维账号": "19585271311",
      "网格": "绥阳县",
      "日期": "3月",
      "呼入总量": 9,
      "一次接听量": 2,
      "一次接听率": 22.22,
      "回拨次数": 0,
      "真实接听率": 22.22,
      "真实未接通次数": 7
    }
  ],
  "遵义-桐梓县": [
    {
      "姓名": "/",
      "装维账号": "19585271351",
      "网格": "桐梓县",
      "日期": "3月",
      "呼入总量": 14,
      "一次接听量": 4,
      "一次接听率": 28.57,
      "回拨次数": 5,
      "真实接听率": 64.29,
      "真实未接通次数": 5
    },
    {
      "姓名": "/",
      "装维账号": "19585271381",
      "网格": "桐梓县",
      "日期": "3月",
      "呼入总量": 21,
      "一次接听量": 7,
      "一次接听率": 33.33,
      "回拨次数": 0,
      "真实接听率": 33.33,
      "真实未接通次数": 14
    },
    {
      "姓名": "/",
      "装维账号": "19585271631",
      "网格": "桐梓县",
      "日期": "3月",
      "呼入总量": 27,
      "一次接听量": 5,
      "一次接听率": 18.52,
      "回拨次数": 13,
      "真实接听率": 66.67,
      "真实未接通次数": 9
    },
    {
      "姓名": "/",
      "装维账号": "19585271733",
      "网格": "桐梓县",
      "日期": "3月",
      "呼入总量": 15,
      "一次接听量": 2,
      "一次接听率": 13.33,
      "回拨次数": 2,
      "真实接听率": 26.67,
      "真实未接通次数": 11
    }
  ],
  "遵义-习水县": [
    {
      "姓名": "/",
      "装维账号": "19585271375",
      "网格": "习水县",
      "日期": "3月",
      "呼入总量": 13,
      "一次接听量": 5,
      "一次接听率": 38.46,
      "回拨次数": 3,
      "真实接听率": 61.54,
      "真实未接通次数": 5
    },
    {
      "姓名": "/",
      "装维账号": "19585271503",
      "网格": "习水县",
      "日期": "3月",
      "呼入总量": 12,
      "一次接听量": 5,
      "一次接听率": 41.67,
      "回拨次数": 3,
      "真实接听率": 66.67,
      "真实未接通次数": 4
    },
    {
      "姓名": "/",
      "装维账号": "19585271613",
      "网格": "习水县",
      "日期": "3月",
      "呼入总量": 14,
      "一次接听量": 1,
      "一次接听率": 7.14,
      "回拨次数": 2,
      "真实接听率": 21.43,
      "真实未接通次数": 11
    },
    {
      "姓名": "/",
      "装维账号": "19585271877",
      "网格": "习水县",
      "日期": "3月",
      "呼入总量": 4,
      "一次接听量": 1,
      "一次接听率": 25.0,
      "回拨次数": 0,
      "真实接听率": 25.0,
      "真实未接通次数": 3
    },
    {
      "姓名": "/",
      "装维账号": "19585272263",
      "网格": "习水县",
      "日期": "3月",
      "呼入总量": 29,
      "一次接听量": 8,
      "一次接听率": 27.59,
      "回拨次数": 8,
      "真实接听率": 55.17,
      "真实未接通次数": 13
    },
    {
      "姓名": "/",
      "装维账号": "19585272353",
      "网格": "习水县",
      "日期": "3月",
      "呼入总量": 16,
      "一次接听量": 9,
      "一次接听率": 56.25,
      "回拨次数": 2,
      "真实接听率": 68.75,
      "真实未接通次数": 5
    },
    {
      "姓名": "/",
      "装维账号": "19585272441",
      "网格": "习水县",
      "日期": "3月",
      "呼入总量": 32,
      "一次接听量": 14,
      "一次接听率": 43.75,
      "回拨次数": 3,
      "真实接听率": 53.13,
      "真实未接通次数": 15
    },
    {
      "姓名": "/",
      "装维账号": "19585272443",
      "网格": "习水县",
      "日期": "3月",
      "呼入总量": 10,
      "一次接听量": 2,
      "一次接听率": 20.0,
      "回拨次数": 3,
      "真实接听率": 50.0,
      "真实未接通次数": 5
    },
    {
      "姓名": "/",
      "装维账号": "19585272584",
      "网格": "习水县",
      "日期": "3月",
      "呼入总量": 27,
      "一次接听量": 12,
      "一次接听率": 44.44,
      "回拨次数": 5,
      "真实接听率": 62.96,
      "真实未接通次数": 10
    },
    {
      "姓名": "/",
      "装维账号": "19585272852",
      "网格": "习水县",
      "日期": "3月",
      "呼入总量": 3,
      "一次接听量": 2,
      "一次接听率": 66.67,
      "回拨次数": 0,
      "真实接听率": 66.67,
      "真实未接通次数": 1
    },
    {
      "姓名": "/",
      "装维账号": "19585273369",
      "网格": "习水县",
      "日期": "3月",
      "呼入总量": 8,
      "一次接听量": 2,
      "一次接听率": 25.0,
      "回拨次数": 0,
      "真实接听率": 25.0,
      "真实未接通次数": 6
    }
  ],
  "遵义-仁怀市": [
    {
      "姓名": "/",
      "装维账号": "19585271415",
      "网格": "仁怀市",
      "日期": "3月",
      "呼入总量": 5,
      "一次接听量": 2,
      "一次接听率": 40.0,
      "回拨次数": 0,
      "真实接听率": 40.0,
      "真实未接通次数": 3
    },
    {
      "姓名": "/",
      "装维账号": "19585271470",
      "网格": "仁怀市",
      "日期": "3月",
      "呼入总量": 26,
      "一次接听量": 2,
      "一次接听率": 7.69,
      "回拨次数": 3,
      "真实接听率": 19.23,
      "真实未接通次数": 21
    },
    {
      "姓名": "/",
      "装维账号": "19585271828",
      "网格": "仁怀市",
      "日期": "3月",
      "呼入总量": 4,
      "一次接听量": 2,
      "一次接听率": 50.0,
      "回拨次数": 0,
      "真实接听率": 50.0,
      "真实未接通次数": 2
    },
    {
      "姓名": "/",
      "装维账号": "19585272130",
      "网格": "仁怀市",
      "日期": "3月",
      "呼入总量": 14,
      "一次接听量": 3,
      "一次接听率": 21.43,
      "回拨次数": 0,
      "真实接听率": 21.43,
      "真实未接通次数": 11
    }
  ],
  "遵义-赤水县": [
    {
      "姓名": "/",
      "装维账号": "19585271433",
      "网格": "赤水县",
      "日期": "3月",
      "呼入总量": 8,
      "一次接听量": 0,
      "一次接听率": 0.0,
      "回拨次数": 1,
      "真实接听率": 12.5,
      "真实未接通次数": 7
    },
    {
      "姓名": "/",
      "装维账号": "19585271609",
      "网格": "赤水县",
      "日期": "3月",
      "呼入总量": 11,
      "一次接听量": 2,
      "一次接听率": 18.18,
      "回拨次数": 5,
      "真实接听率": 63.64,
      "真实未接通次数": 4
    },
    {
      "姓名": "/",
      "装维账号": "19585271755",
      "网格": "赤水县",
      "日期": "3月",
      "呼入总量": 16,
      "一次接听量": 5,
      "一次接听率": 31.25,
      "回拨次数": 5,
      "真实接听率": 62.5,
      "真实未接通次数": 6
    }
  ],
  "遵义-新蒲区": [
    {
      "姓名": "/",
      "装维账号": "19585271812",
      "网格": "新蒲区",
      "日期": "3月",
      "呼入总量": 23,
      "一次接听量": 4,
      "一次接听率": 17.39,
      "回拨次数": 5,
      "真实接听率": 39.13,
      "真实未接通次数": 14
    },
    {
      "姓名": "/",
      "装维账号": "19585271852",
      "网格": "新蒲区",
      "日期": "3月",
      "呼入总量": 3,
      "一次接听量": 1,
      "一次接听率": 33.33,
      "回拨次数": 1,
      "真实接听率": 66.67,
      "真实未接通次数": 1
    },
    {
      "姓名": "/",
      "装维账号": "19585271855",
      "网格": "新蒲区",
      "日期": "3月",
      "呼入总量": 19,
      "一次接听量": 3,
      "一次接听率": 15.79,
      "回拨次数": 1,
      "真实接听率": 21.05,
      "真实未接通次数": 15
    },
    {
      "姓名": "/",
      "装维账号": "19585271896",
      "网格": "新蒲区",
      "日期": "3月",
      "呼入总量": 17,
      "一次接听量": 11,
      "一次接听率": 64.71,
      "回拨次数": 0,
      "真实接听率": 64.71,
      "真实未接通次数": 6
    },
    {
      "姓名": "/",
      "装维账号": "19585271986",
      "网格": "新蒲区",
      "日期": "3月",
      "呼入总量": 6,
      "一次接听量": 4,
      "一次接听率": 66.67,
      "回拨次数": 0,
      "真实接听率": 66.67,
      "真实未接通次数": 2
    },
    {
      "姓名": "/",
      "装维账号": "19585272063",
      "网格": "新蒲区",
      "日期": "3月",
      "呼入总量": 29,
      "一次接听量": 18,
      "一次接听率": 62.07,
      "回拨次数": 2,
      "真实接听率": 68.97,
      "真实未接通次数": 9
    }
  ],
  "遵义-汇川区": [
    {
      "姓名": "/",
      "装维账号": "19585272230",
      "网格": "汇川区",
      "日期": "3月",
      "呼入总量": 44,
      "一次接听量": 9,
      "一次接听率": 20.45,
      "回拨次数": 5,
      "真实接听率": 31.82,
      "真实未接通次数": 30
    },
    {
      "姓名": "/",
      "装维账号": "19585272978",
      "网格": "汇川区",
      "日期": "3月",
      "呼入总量": 14,
      "一次接听量": 5,
      "一次接听率": 35.71,
      "回拨次数": 4,
      "真实接听率": 64.29,
      "真实未接通次数": 5
    }
  ]
}